{
 "formatVersion": "0.1",
 "columns": [
  "Category",
  "URS ID",
  "SRS ID",
  "Subtitle",
  "Release",
  "Quality critial requirements",
  "On-Premise"
 ],
 "records": [
  {
   "id": "82f3fef9-9c03-4c86-9af1-15c8dff36718",
   "idx": 0,
   "data": [
    "vulgaris attollo audentia",
    "KE_URS_31",
    "SRS_1",
    "Torrens deludo vulgus tergum arcus crepusculum virga tabula.",
    "9.3.9",
    "",
    "N/A"
   ]
  },
  {
   "id": "458d71ab-3f72-4a13-98ec-32599bca056e",
   "idx": 1,
   "data": [
    "basium textus verbum",
    "KE_URS_15",
    "SRS_2",
    "Sumo auctor iure defluo cilicium dens.",
    "8.0.7",
    "",
    ""
   ]
  },
  {
   "id": "3a794717-34d8-4e86-9907-190847952cc6",
   "idx": 2,
   "data": [
    "maxime ascisco quasi",
    "KE_URS_79",
    "SRS_3",
    "Odio voveo vero vitiosus triduana communis venia vulgo vetus.",
    "2.7.2",
    "Yes",
    ""
   ]
  },
  {
   "id": "8abbb417-72d6-4ed5-b305-f9d8b4b27de4",
   "idx": 3,
   "data": [
    "talis tui solitudo",
    "KE_URS_33",
    "SRS_4",
    "Atque tres curis sed administratio inflammatio.",
    "6.0.5",
    "Yes",
    ""
   ]
  },
  {
   "id": "015a17a4-084d-4a5a-8d84-ecfc82a8f0c4",
   "idx": 4,
   "data": [
    "varietas utrimque bellum",
    "KE_URS_82",
    "SRS_5",
    "Tricesimus campana audacia.",
    "6.7.1",
    "",
    ""
   ]
  },
  {
   "id": "adead5cf-1081-4508-8327-e53277e6bb74",
   "idx": 5,
   "data": [
    "vulgaris attollo audentia",
    "KE_URS_84",
    "SRS_6",
    "Cito ubi vita tripudio ducimus adflicto omnis.",
    "0.3.2",
    "Yes",
    ""
   ]
  },
  {
   "id": "ffdaee3a-76b3-4bde-8065-1c95e18943e2",
   "idx": 6,
   "data": [
    "sordeo civis trans",
    "KE_URS_24",
    "SRS_7",
    "Molestiae decerno causa compono claustrum tero cena attero conor molestiae.",
    "1.8.6",
    "",
    ""
   ]
  },
  {
   "id": "4d0f3db6-2549-43f8-8ba8-d64fdc13e200",
   "idx": 7,
   "data": [
    "bos baiulus surgo",
    "KE_URS_11",
    "SRS_8",
    "Tabula supplanto et contabesco crudelis synagoga.",
    "7.4.6",
    "Yes",
    ""
   ]
  },
  {
   "id": "57b53ff9-8fac-4002-b939-21d218a0ce94",
   "idx": 8,
   "data": [
    "patruus pecto cuppedia",
    "KE_URS_50",
    "SRS_9",
    "Articulus collum ager vulgus stabilis argentum victus quas acquiro.",
    "4.3.5",
    "Yes",
    ""
   ]
  },
  {
   "id": "e2f02c7f-138e-4295-8086-f92a17c06007",
   "idx": 9,
   "data": [
    "bos baiulus surgo",
    "KE_URS_8",
    "SRS_10",
    "Bibo aufero spes demens ter adeo volup carmen.",
    "5.2.2",
    "Yes",
    ""
   ]
  },
  {
   "id": "50b4af32-881e-43a0-aab4-81767efbdaa9",
   "idx": 10,
   "data": [
    "vestrum vicinus tabgo",
    "KE_URS_92",
    "SRS_11",
    "Absque celo clementia in.",
    "2.9.6",
    "",
    ""
   ]
  },
  {
   "id": "2ae878db-10ca-45f4-b96b-4133cf133b82",
   "idx": 11,
   "data": [
    "ducimus doloribus damnatio",
    "KE_URS_2",
    "SRS_12",
    "Truculenter eos vicissitudo ciminatio tonsor depromo ipsum terreo video.",
    "7.5.5",
    "",
    ""
   ]
  },
  {
   "id": "b30f2503-8e3c-40d2-9fca-4dcfac5ef70c",
   "idx": 12,
   "data": [
    "adopto demoror sint",
    "KE_URS_26",
    "SRS_13",
    "Tam praesentium adicio universe iusto cavus.",
    "8.4.5",
    "Yes",
    ""
   ]
  },
  {
   "id": "cb0b168b-b7d5-4af0-9d30-71499c4bb0e9",
   "idx": 13,
   "data": [
    "adopto demoror sint",
    "KE_URS_51",
    "SRS_14",
    "Aranea turbo vir ter approbo.",
    "9.5.3",
    "Yes",
    ""
   ]
  },
  {
   "id": "4af59b3a-0f69-4ccc-8616-8180c7af81c1",
   "idx": 14,
   "data": [
    "comparo aegre corroboro",
    "KE_URS_60",
    "SRS_15",
    "Crepusculum voco debilito accedo.",
    "4.2.3",
    "",
    "N/A"
   ]
  },
  {
   "id": "6dcb1c19-2a7d-41a8-b5ab-2eefde175f1d",
   "idx": 15,
   "data": [
    "somnus ratione valde",
    "KE_URS_27",
    "SRS_16",
    "Omnis dens cupiditas spargo.",
    "8.5.1",
    "",
    ""
   ]
  },
  {
   "id": "589e6a8e-9384-429e-860a-a189e70ae6e8",
   "idx": 16,
   "data": [
    "arcus assentator assentator",
    "KE_URS_32",
    "SRS_17",
    "Caveo aperte tempus civitas balbus audax derelinquo stillicidium delego.",
    "8.6.5",
    "",
    ""
   ]
  },
  {
   "id": "1a585f1b-52a9-4607-9b0a-27ed65c3b0c7",
   "idx": 17,
   "data": [
    "somnus ratione valde",
    "KE_URS_58",
    "SRS_18",
    "Commemoro teneo temporibus apud pariatur argumentum sumo animi cognatus desolo.",
    "7.3.9",
    "Yes",
    ""
   ]
  },
  {
   "id": "dad3dee4-596d-4012-9c60-0ed943f8ba73",
   "idx": 18,
   "data": [
    "somnus ratione valde",
    "KE_URS_61",
    "SRS_19",
    "Canis contigo accommodo approbo sed tenus tamquam vitae adimpleo vaco.",
    "0.0.2",
    "Yes",
    ""
   ]
  },
  {
   "id": "9522effd-a3c2-49d8-911d-5cc3611ea6e8",
   "idx": 19,
   "data": [
    "claudeo volva turba",
    "KE_URS_35",
    "SRS_20",
    "Aufero vorax voluptatem considero pectus bardus.",
    "4.7.9",
    "Yes",
    ""
   ]
  },
  {
   "id": "878e9fae-766b-4ee6-8c44-5d0bbbd6b915",
   "idx": 20,
   "data": [
    "ustilo creo crebro",
    "KE_URS_75",
    "SRS_21",
    "Alo considero talus.",
    "4.1.6",
    "",
    ""
   ]
  },
  {
   "id": "dd54a80f-2ad9-422a-bf87-a2b4e9997e80",
   "idx": 21,
   "data": [
    "cogo a terra",
    "KE_URS_81",
    "SRS_22",
    "Deleniti acsi decerno ait capitulus coniecto agnosco.",
    "0.1.2",
    "Yes",
    ""
   ]
  },
  {
   "id": "d3cadfbd-3955-4064-a012-26b4984bfd20",
   "idx": 22,
   "data": [
    "sordeo civis trans",
    "KE_URS_21",
    "SRS_23",
    "Laborum decumbo similique thalassinus.",
    "4.0.4",
    "Yes",
    ""
   ]
  },
  {
   "id": "11e25f7b-852a-45b6-99f0-dc0bfd7c6457",
   "idx": 23,
   "data": [
    "ducimus doloribus damnatio",
    "KE_URS_69",
    "SRS_24",
    "Vobis conor demo custodia adficio cervus sint copia.",
    "1.2.1",
    "Yes",
    ""
   ]
  },
  {
   "id": "367c6d2c-ed67-4802-9d9e-2aecaaca8ef7",
   "idx": 24,
   "data": [
    "consuasor audentia ab",
    "KE_URS_23",
    "SRS_25",
    "Vere caries surculus veniam magnam.",
    "1.7.7",
    "Yes",
    ""
   ]
  },
  {
   "id": "9946b079-91b3-4120-a6e2-284daba88e6a",
   "idx": 25,
   "data": [
    "somnus ratione valde",
    "KE_URS_47",
    "SRS_26",
    "Compello acquiro victus demulceo cometes approbo aspicio conturbo caries velut.",
    "4.8.7",
    "",
    ""
   ]
  },
  {
   "id": "3cd61675-6605-4ea5-91df-3c3f970288cd",
   "idx": 26,
   "data": [
    "patruus pecto cuppedia",
    "KE_URS_45",
    "SRS_27",
    "Tyrannus stipes caelum appello quibusdam validus.",
    "3.0.4",
    "Yes",
    ""
   ]
  },
  {
   "id": "b0a5de58-b3b7-44b1-9931-84aed67ff7de",
   "idx": 27,
   "data": [
    "maxime ascisco quasi",
    "KE_URS_22",
    "SRS_28",
    "Vesper laboriosam vilis.",
    "5.4.9",
    "",
    ""
   ]
  },
  {
   "id": "e8cafc4c-f8b4-471d-9184-008e27ab546a",
   "idx": 28,
   "data": [
    "cursim denique torrens",
    "KE_URS_72",
    "SRS_29",
    "Cenaculum ulterius studio.",
    "0.5.8",
    "",
    ""
   ]
  },
  {
   "id": "93c02818-f6fa-4647-9740-08226f895c6c",
   "idx": 29,
   "data": [
    "basium textus verbum",
    "KE_URS_68",
    "SRS_30",
    "Tamisium tenuis adhaero desolo benigne somniculosus aggero vapulus textor.",
    "4.8.0",
    "",
    ""
   ]
  },
  {
   "id": "593bb5b7-abfc-4abc-9ffc-f5ee76771113",
   "idx": 30,
   "data": [
    "sordeo civis trans",
    "KE_URS_15",
    "SRS_31",
    "Tam denego denique damno tamisium.",
    "1.0.1",
    "Yes",
    ""
   ]
  },
  {
   "id": "e27014fa-adae-49a2-b464-f423a57a7e50",
   "idx": 31,
   "data": [
    "nostrum ulciscor tyrannus",
    "KE_URS_45",
    "SRS_32",
    "Taedium perferendis praesentium censura.",
    "7.1.3",
    "Yes",
    ""
   ]
  },
  {
   "id": "9690c3dc-11d7-4799-9275-ec78c7c65ef6",
   "idx": 32,
   "data": [
    "vestrum vicinus tabgo",
    "KE_URS_95",
    "SRS_33",
    "Eum alii consuasor damno video umquam tenetur dicta suggero aeternus.",
    "0.4.9",
    "Yes",
    ""
   ]
  },
  {
   "id": "4ebe9d54-5421-4c5b-9b75-8471e77b4b88",
   "idx": 33,
   "data": [
    "adopto demoror sint",
    "KE_URS_41",
    "SRS_34",
    "Depopulo ulterius est comminor deduco ver fuga vitae sono.",
    "3.5.3",
    "Yes",
    "N/A"
   ]
  },
  {
   "id": "4468ff7c-42e2-48a2-90a5-ffa519c44b98",
   "idx": 34,
   "data": [
    "patruus pecto cuppedia",
    "KE_URS_93",
    "SRS_35",
    "Spero vulnus spiculum velum tardus caterva apostolus neque certus.",
    "8.4.0",
    "Yes",
    ""
   ]
  },
  {
   "id": "3eef42dd-643a-4436-99aa-616ee33a43bd",
   "idx": 35,
   "data": [
    "basium textus verbum",
    "KE_URS_30",
    "SRS_36",
    "Stella sonitus suppono corrupti argumentum subiungo atque admiratio abundans.",
    "0.6.7",
    "",
    ""
   ]
  },
  {
   "id": "c080586f-37f6-4fc8-ab55-e17ce77b560e",
   "idx": 36,
   "data": [
    "consuasor audentia ab",
    "KE_URS_54",
    "SRS_37",
    "Sono adfectus tot.",
    "9.5.3",
    "",
    ""
   ]
  },
  {
   "id": "3e01602d-7310-43f1-bb9f-afcab15089ee",
   "idx": 37,
   "data": [
    "ducimus doloribus damnatio",
    "KE_URS_81",
    "SRS_38",
    "Quisquam certus spoliatio communis stips.",
    "1.0.0",
    "",
    ""
   ]
  },
  {
   "id": "98f6b5a7-28cd-4a1e-bb71-5bc29953945d",
   "idx": 38,
   "data": [
    "antepono aestivus tabgo",
    "KE_URS_1",
    "SRS_39",
    "Benevolentia aqua laboriosam acer caveo aestivus curiositas capitulus succurro summopere.",
    "4.1.6",
    "Yes",
    ""
   ]
  },
  {
   "id": "c36ef3e1-dab2-4181-a53a-42273e54a907",
   "idx": 39,
   "data": [
    "talis tui solitudo",
    "KE_URS_24",
    "SRS_40",
    "Virgo tamen sum numquam bene contra tamisium conitor voluntarius credo.",
    "7.6.8",
    "Yes",
    "N/A"
   ]
  },
  {
   "id": "f7f7f37f-a8ac-4cb8-82ee-15647a991972",
   "idx": 40,
   "data": [
    "cursim denique torrens",
    "KE_URS_33",
    "SRS_41",
    "Aestus conculco crux.",
    "8.6.9",
    "Yes",
    ""
   ]
  },
  {
   "id": "c0890b50-706d-4321-ae25-825b42f240c2",
   "idx": 41,
   "data": [
    "conscendo una toties",
    "KE_URS_4",
    "SRS_42",
    "Vae expedita suadeo temeritas vesica deleo statim animus curvo.",
    "0.2.6",
    "Yes",
    ""
   ]
  },
  {
   "id": "1b70b30d-5ee1-4480-bd12-16daa9b83a31",
   "idx": 42,
   "data": [
    "somnus ratione valde",
    "KE_URS_55",
    "SRS_43",
    "Nihil ea considero corporis appono dolore cena terror optio.",
    "0.2.5",
    "",
    ""
   ]
  },
  {
   "id": "340c1f29-1346-4eb9-8236-7b383b29f2be",
   "idx": 43,
   "data": [
    "vacuus nostrum doloribus",
    "KE_URS_74",
    "SRS_44",
    "Surgo utrum sperno.",
    "5.0.5",
    "Yes",
    ""
   ]
  },
  {
   "id": "b54068f5-a753-4fdc-9bf2-aa115da9f4a1",
   "idx": 44,
   "data": [
    "antepono aestivus tabgo",
    "KE_URS_33",
    "SRS_45",
    "Admiratio defluo ustilo venia cenaculum.",
    "9.7.7",
    "",
    ""
   ]
  },
  {
   "id": "7f9730c6-1949-4287-b3a3-3fd64f2e1d3e",
   "idx": 45,
   "data": [
    "sufficio odit vesica",
    "KE_URS_64",
    "SRS_46",
    "Ambitus tot architecto validus ceno.",
    "6.5.6",
    "Yes",
    ""
   ]
  },
  {
   "id": "b9635eb6-3a97-43fd-8e75-df5fdbfbefeb",
   "idx": 46,
   "data": [
    "comparo aegre corroboro",
    "KE_URS_64",
    "SRS_47",
    "Antepono appello strues umquam tabula sapiente stillicidium terreo aptus recusandae.",
    "8.3.1",
    "Yes",
    ""
   ]
  },
  {
   "id": "2ef75749-d87d-43fd-90ad-15118e025ef7",
   "idx": 47,
   "data": [
    "arcus assentator assentator",
    "KE_URS_45",
    "SRS_48",
    "Antiquus nihil tremo cena verecundia.",
    "0.7.9",
    "Yes",
    ""
   ]
  },
  {
   "id": "777a915f-f5b3-4a59-b2d9-adbef66e3fc8",
   "idx": 48,
   "data": [
    "aliquam coadunatio abutor",
    "KE_URS_85",
    "SRS_49",
    "Expedita molestias sponte volo.",
    "1.7.7",
    "Yes",
    "N/A"
   ]
  },
  {
   "id": "f2a7228a-b340-4133-b280-1dab3a41cfb9",
   "idx": 49,
   "data": [
    "conscendo una toties",
    "KE_URS_32",
    "SRS_50",
    "Vulpes sapiente spero tantum tracto cerno avarus vaco.",
    "9.2.2",
    "Yes",
    ""
   ]
  },
  {
   "id": "1962f57b-199f-4dc6-aeac-c220ef06ba50",
   "idx": 50,
   "data": [
    "depromo accusamus paens",
    "KE_URS_62",
    "SRS_51",
    "Astrum summopere derelinquo cena asperiores vox nemo tenuis anser auctus.",
    "1.9.9",
    "Yes",
    ""
   ]
  },
  {
   "id": "7ccb1a6d-e915-4e26-8f7f-95893b249bc3",
   "idx": 51,
   "data": [
    "patruus pecto cuppedia",
    "KE_URS_23",
    "SRS_52",
    "Tonsor video aegrus.",
    "0.3.3",
    "",
    ""
   ]
  },
  {
   "id": "2494c782-a815-47ba-9375-ff23268a7d6a",
   "idx": 52,
   "data": [
    "claudeo volva turba",
    "KE_URS_27",
    "SRS_53",
    "Vinculum substantia est crepusculum ago valens delectatio ciminatio.",
    "0.4.2",
    "Yes",
    "N/A"
   ]
  },
  {
   "id": "d42920cf-59d2-46ad-a35c-c5003e9dd0d7",
   "idx": 53,
   "data": [
    "vergo degenero succurro",
    "KE_URS_37",
    "SRS_54",
    "At benevolentia admoveo vilis spes adaugeo dedecor torrens torqueo.",
    "7.5.7",
    "Yes",
    ""
   ]
  },
  {
   "id": "3a57a34d-d537-4e10-9722-c42a671229fe",
   "idx": 54,
   "data": [
    "vacuus nostrum doloribus",
    "KE_URS_26",
    "SRS_55",
    "Viscus cibus votum.",
    "5.3.3",
    "",
    ""
   ]
  },
  {
   "id": "d79bd83b-781f-4ab3-a674-ddf7e95d45d7",
   "idx": 55,
   "data": [
    "adopto demoror sint",
    "KE_URS_45",
    "SRS_56",
    "Versus caute defessus arbustum adficio dedecor modi dedecor volo studio.",
    "2.4.1",
    "",
    ""
   ]
  },
  {
   "id": "312136d4-e758-4280-901d-6104deb2a1c4",
   "idx": 56,
   "data": [
    "cursim denique torrens",
    "KE_URS_61",
    "SRS_57",
    "Turba volutabrum amo arceo.",
    "1.8.5",
    "",
    ""
   ]
  },
  {
   "id": "1b4aee85-0aa5-47a9-ab5a-7f14e760c5ee",
   "idx": 57,
   "data": [
    "maxime ascisco quasi",
    "KE_URS_48",
    "SRS_58",
    "Dens talio cras tabula sol delinquo clamo velociter considero velut.",
    "6.9.0",
    "Yes",
    "N/A"
   ]
  },
  {
   "id": "a5f5eda4-359a-48d3-9e33-23c461d5fb80",
   "idx": 58,
   "data": [
    "tamquam abeo usus",
    "KE_URS_27",
    "SRS_59",
    "Thema virga cervus attonbitus.",
    "0.4.0",
    "",
    ""
   ]
  },
  {
   "id": "832109c6-16da-40e8-b28b-0a1a4859f951",
   "idx": 59,
   "data": [
    "varietas utrimque bellum",
    "KE_URS_85",
    "SRS_60",
    "Natus demum excepturi summa unus.",
    "2.6.5",
    "Yes",
    ""
   ]
  },
  {
   "id": "626d85e3-0847-4c60-8a6c-edbee02673fa",
   "idx": 60,
   "data": [
    "basium textus verbum",
    "KE_URS_15",
    "SRS_61",
    "Cibo iusto caecus apparatus.",
    "5.9.0",
    "Yes",
    ""
   ]
  },
  {
   "id": "e36b4070-cd12-4277-90fe-717825e8d87c",
   "idx": 61,
   "data": [
    "angulus beatae voco",
    "KE_URS_30",
    "SRS_62",
    "Accommodo carbo denique.",
    "9.8.6",
    "Yes",
    "N/A"
   ]
  },
  {
   "id": "3a23e513-ff6d-4965-9c6a-770d46d73822",
   "idx": 62,
   "data": [
    "vergo degenero succurro",
    "KE_URS_92",
    "SRS_63",
    "Vulpes cui bene auditor.",
    "3.0.9",
    "Yes",
    ""
   ]
  },
  {
   "id": "a64e7b53-933c-488c-9799-84ed5a38e377",
   "idx": 63,
   "data": [
    "veritas tabesco delibero",
    "KE_URS_47",
    "SRS_64",
    "Sollicito vel neque advoco accommodo bellicus placeat.",
    "9.9.5",
    "Yes",
    ""
   ]
  },
  {
   "id": "4d39d5e3-be76-4549-8f67-5d72e13a700f",
   "idx": 64,
   "data": [
    "antepono aestivus tabgo",
    "KE_URS_44",
    "SRS_65",
    "Dapifer argumentum autem bos abutor arbor celer creptio est beneficium.",
    "8.7.5",
    "",
    ""
   ]
  },
  {
   "id": "cd9b8d1a-c1ce-43af-9e12-e25a1d6d4158",
   "idx": 65,
   "data": [
    "vacuus nostrum doloribus",
    "KE_URS_58",
    "SRS_66",
    "Suus sophismata aspernatur vos.",
    "5.1.3",
    "Yes",
    ""
   ]
  },
  {
   "id": "9a9d46a9-761c-4517-a49d-79226d0420ce",
   "idx": 66,
   "data": [
    "aeneus capillus substantia",
    "KE_URS_36",
    "SRS_67",
    "Verbum censura appello sollers umerus bene cras.",
    "6.8.5",
    "Yes",
    ""
   ]
  },
  {
   "id": "fddc0cdb-76e3-45f3-bef7-baf0bd198642",
   "idx": 67,
   "data": [
    "vacuus nostrum doloribus",
    "KE_URS_49",
    "SRS_68",
    "Bellicus cimentarius repellendus adeptio aureus aranea arma.",
    "9.4.1",
    "Yes",
    ""
   ]
  },
  {
   "id": "d55b36aa-6432-4253-bd40-aa3eccedb71b",
   "idx": 68,
   "data": [
    "nostrum ulciscor tyrannus",
    "KE_URS_10",
    "SRS_69",
    "Adopto deprimo delectatio rerum.",
    "4.0.5",
    "Yes",
    ""
   ]
  },
  {
   "id": "bf406b3e-509e-421e-9232-4caa1ecb096e",
   "idx": 69,
   "data": [
    "varietas utrimque bellum",
    "KE_URS_49",
    "SRS_70",
    "Coepi conforto neque solum bestia amaritudo circumvenio suscipit.",
    "2.8.5",
    "Yes",
    ""
   ]
  },
  {
   "id": "27237e83-0ee5-4b67-9102-08431d2e3e36",
   "idx": 70,
   "data": [
    "angulus beatae voco",
    "KE_URS_50",
    "SRS_71",
    "Quisquam tergiversatio quod accusator delego.",
    "1.2.0",
    "Yes",
    ""
   ]
  },
  {
   "id": "74dd8299-55f3-479a-af52-f87e2c10b80b",
   "idx": 71,
   "data": [
    "veritas tabesco delibero",
    "KE_URS_2",
    "SRS_72",
    "Calcar thorax avarus suscipit cetera velociter cruentus abscido cupio.",
    "5.4.7",
    "",
    "N/A"
   ]
  },
  {
   "id": "81192376-dd4b-47fc-87a9-c7a076475c26",
   "idx": 72,
   "data": [
    "adopto demoror sint",
    "KE_URS_98",
    "SRS_73",
    "Confero cohors cibus aufero conculco curiositas officiis error aiunt.",
    "5.4.9",
    "",
    ""
   ]
  },
  {
   "id": "8df0a9b7-a59a-4520-a3cc-6e105e88a4e0",
   "idx": 73,
   "data": [
    "claudeo volva turba",
    "KE_URS_43",
    "SRS_74",
    "Administratio brevis collum baiulus theologus deleniti titulus bellicus nobis arcesso.",
    "0.0.5",
    "Yes",
    ""
   ]
  },
  {
   "id": "17f5b3dc-6732-40cd-aac2-810e04d1beef",
   "idx": 74,
   "data": [
    "perferendis talis culpa",
    "KE_URS_81",
    "SRS_75",
    "Solium sub tactus subiungo.",
    "5.0.8",
    "Yes",
    "N/A"
   ]
  },
  {
   "id": "9d93a4cf-bec0-4829-98d4-50dee48ace3a",
   "idx": 75,
   "data": [
    "arcus assentator assentator",
    "KE_URS_17",
    "SRS_76",
    "Vestrum alioqui ambulo tot cicuta contra.",
    "6.5.4",
    "Yes",
    ""
   ]
  },
  {
   "id": "978aba03-f06a-44e9-a8e8-1d16aad6c7a7",
   "idx": 76,
   "data": [
    "varietas utrimque bellum",
    "KE_URS_94",
    "SRS_77",
    "Vulnus sint amplus incidunt appello.",
    "6.2.9",
    "Yes",
    ""
   ]
  },
  {
   "id": "b86e0522-e883-4ce6-a244-d6f40e2bfabf",
   "idx": 77,
   "data": [
    "aliquam coadunatio abutor",
    "KE_URS_97",
    "SRS_78",
    "Stultus alius deripio bardus ager abbas defaeco appono.",
    "7.4.3",
    "",
    ""
   ]
  },
  {
   "id": "0506d604-37bb-423b-8100-c80a6c2c2ba9",
   "idx": 78,
   "data": [
    "arcus assentator assentator",
    "KE_URS_51",
    "SRS_79",
    "Tenuis arcesso certus tibi quisquam sophismata compono auditor porro.",
    "9.5.0",
    "Yes",
    ""
   ]
  },
  {
   "id": "5053d303-bd66-464f-a34c-924093e34882",
   "idx": 79,
   "data": [
    "arcus assentator assentator",
    "KE_URS_91",
    "SRS_80",
    "Voco adstringo tabesco.",
    "6.1.1",
    "",
    ""
   ]
  },
  {
   "id": "2b3f8b2b-18d9-4958-92b5-4f78c6a41731",
   "idx": 80,
   "data": [
    "vis aggredior capto",
    "KE_URS_89",
    "SRS_81",
    "Contra torqueo thymbra vomito cilicium.",
    "8.7.6",
    "Yes",
    ""
   ]
  },
  {
   "id": "3ffcc117-7c72-4976-895b-11909c651f91",
   "idx": 81,
   "data": [
    "sufficio odit vesica",
    "KE_URS_70",
    "SRS_82",
    "Coruscus laborum solum error coaegresco cur auctus consequatur claustrum defluo.",
    "4.7.4",
    "",
    ""
   ]
  },
  {
   "id": "02e5e247-f101-4198-abc5-fd06c27780f4",
   "idx": 82,
   "data": [
    "perferendis talis culpa",
    "KE_URS_22",
    "SRS_83",
    "Bellicus ulciscor cubitum defungo vomito velut ulciscor acquiro tardus acidus.",
    "5.0.7",
    "Yes",
    ""
   ]
  },
  {
   "id": "d2571529-439a-4e66-ae5a-9e9ca55f3ed7",
   "idx": 83,
   "data": [
    "aeneus capillus substantia",
    "KE_URS_15",
    "SRS_84",
    "Thorax victus natus videlicet aiunt coaegresco mollitia conturbo.",
    "7.5.5",
    "",
    ""
   ]
  },
  {
   "id": "6fcd0bfd-6747-4b8e-a2a8-0934b56e7d8b",
   "idx": 84,
   "data": [
    "nostrum ulciscor tyrannus",
    "KE_URS_51",
    "SRS_85",
    "Decretum possimus demens quas totidem comitatus sophismata voco tyrannus.",
    "9.2.9",
    "Yes",
    "N/A"
   ]
  },
  {
   "id": "ca08eedf-e977-483a-8111-9d2720940c98",
   "idx": 85,
   "data": [
    "ustilo creo crebro",
    "KE_URS_58",
    "SRS_86",
    "Ver celebrer corona avaritia apostolus cilicium vestigium sufficio denique.",
    "7.3.0",
    "Yes",
    ""
   ]
  },
  {
   "id": "2ab2313e-fc27-4dda-8692-88cff80de5a6",
   "idx": 86,
   "data": [
    "claudeo volva turba",
    "KE_URS_8",
    "SRS_87",
    "Calco decimus sequi acies trado qui cohibeo.",
    "5.7.8",
    "Yes",
    ""
   ]
  },
  {
   "id": "7bb87405-a733-416a-8243-330de8c48717",
   "idx": 87,
   "data": [
    "aliquam coadunatio abutor",
    "KE_URS_20",
    "SRS_88",
    "Beatae color ustulo.",
    "7.8.7",
    "Yes",
    ""
   ]
  },
  {
   "id": "5b7b18b0-1295-404d-b2e7-d7089d444668",
   "idx": 88,
   "data": [
    "sordeo civis trans",
    "KE_URS_87",
    "SRS_89",
    "Copia curtus currus auditor terebro vel tergeo amor adnuo apostolus.",
    "8.9.9",
    "Yes",
    ""
   ]
  },
  {
   "id": "2e590521-5c11-4f0d-8891-46ebba53d663",
   "idx": 89,
   "data": [
    "ustilo creo crebro",
    "KE_URS_97",
    "SRS_90",
    "Non strues paulatim sollicito abutor tyrannus laudantium avarus claustrum.",
    "1.2.4",
    "Yes",
    ""
   ]
  },
  {
   "id": "6c5e19c8-effa-4e95-9129-9790c70b2c59",
   "idx": 90,
   "data": [
    "talis tui solitudo",
    "KE_URS_82",
    "SRS_91",
    "Tego umbra terreo arcus natus viridis alienus velut asperiores tepidus.",
    "6.7.1",
    "",
    ""
   ]
  },
  {
   "id": "3947cf99-5241-4c52-90ce-9b4df3fb5d08",
   "idx": 91,
   "data": [
    "antepono aestivus tabgo",
    "KE_URS_92",
    "SRS_92",
    "Vulticulus cibo carpo voluptatem corrigo theologus vociferor convoco voro surgo.",
    "4.3.9",
    "",
    ""
   ]
  },
  {
   "id": "023541a5-575a-4b64-90d8-37eac4ced9a0",
   "idx": 92,
   "data": [
    "antepono aestivus tabgo",
    "KE_URS_82",
    "SRS_93",
    "Adeptio statua compello alveus.",
    "0.0.4",
    "",
    ""
   ]
  },
  {
   "id": "0a507d3f-0c47-45af-bd67-cce00f7d1938",
   "idx": 93,
   "data": [
    "conscendo una toties",
    "KE_URS_8",
    "SRS_94",
    "Taedium adimpleo vesica aegre aufero stillicidium vespillo eos alter texo.",
    "7.5.0",
    "",
    ""
   ]
  },
  {
   "id": "580ee258-a8e1-4e58-a9d3-c3bf777b1e03",
   "idx": 94,
   "data": [
    "ustilo creo crebro",
    "KE_URS_46",
    "SRS_95",
    "Facilis urbanus tui delibero aliquam.",
    "5.7.4",
    "Yes",
    ""
   ]
  },
  {
   "id": "f89ef1a0-74e2-4eb1-90de-a79a7bbcb6ad",
   "idx": 95,
   "data": [
    "vulgaris attollo audentia",
    "KE_URS_46",
    "SRS_96",
    "Utrimque cubicularis summisse velociter adfero degenero.",
    "1.8.1",
    "Yes",
    ""
   ]
  },
  {
   "id": "8e5cbefe-e384-42d1-93df-52cadef0e9ed",
   "idx": 96,
   "data": [
    "adopto demoror sint",
    "KE_URS_80",
    "SRS_97",
    "Tempora corrumpo verbum stips tabgo assentator talis peccatus sunt.",
    "4.8.4",
    "Yes",
    ""
   ]
  },
  {
   "id": "042ec950-3beb-465e-9d5b-ff02da43488b",
   "idx": 97,
   "data": [
    "cogo a terra",
    "KE_URS_33",
    "SRS_98",
    "Venio curatio depraedor quos armarium.",
    "5.3.5",
    "Yes",
    "N/A"
   ]
  },
  {
   "id": "7ddc50c6-9c95-46c2-a942-6e856b5e69f0",
   "idx": 98,
   "data": [
    "vis aggredior capto",
    "KE_URS_46",
    "SRS_99",
    "Somniculosus adulatio illo solvo tabella attero.",
    "8.1.9",
    "Yes",
    ""
   ]
  },
  {
   "id": "c17de724-b46c-4bee-bdd8-fb5961dc1850",
   "idx": 99,
   "data": [
    "ducimus doloribus damnatio",
    "KE_URS_2",
    "SRS_100",
    "Agnitio derelinquo sortitus adamo adficio.",
    "9.2.4",
    "Yes",
    ""
   ]
  },
  {
   "id": "d9f960cf-a0e6-4697-b9f2-025f98efd6e2",
   "idx": 100,
   "data": [
    "somnus ratione valde",
    "KE_URS_82",
    "SRS_101",
    "Quas usitas sufficio torqueo clementia creator abstergo stips adduco.",
    "9.6.6",
    "Yes",
    ""
   ]
  },
  {
   "id": "9d9eb8c7-ef38-44b3-97cf-b3c39c543f5a",
   "idx": 101,
   "data": [
    "arcus assentator assentator",
    "KE_URS_42",
    "SRS_102",
    "Aut fuga coniecto expedita aegrus vox angulus delibero.",
    "0.6.3",
    "",
    ""
   ]
  },
  {
   "id": "66904aa0-2ed8-4601-8547-7a6a068878ad",
   "idx": 102,
   "data": [
    "vis aggredior capto",
    "KE_URS_67",
    "SRS_103",
    "Depulso doloremque defaeco conduco vivo vilitas benevolentia tyrannus aegrotatio.",
    "7.0.4",
    "",
    ""
   ]
  },
  {
   "id": "2e5e7865-a1a5-471d-8ea9-1c07ecad7b00",
   "idx": 103,
   "data": [
    "ducimus doloribus damnatio",
    "KE_URS_14",
    "SRS_104",
    "Adaugeo aperiam tepesco cedo ante venio chirographum nihil clarus.",
    "1.1.5",
    "",
    ""
   ]
  },
  {
   "id": "405cea88-a5c7-4e18-8a15-1028456d21a9",
   "idx": 104,
   "data": [
    "sordeo civis trans",
    "KE_URS_97",
    "SRS_105",
    "Ambulo aduro temptatio.",
    "7.0.8",
    "",
    ""
   ]
  },
  {
   "id": "e2928151-b9e6-4cb0-a6dd-3a4304834003",
   "idx": 105,
   "data": [
    "aliqua crepusculum celer",
    "KE_URS_62",
    "SRS_106",
    "Tumultus attollo delego at hic vapulus absum harum officia cariosus.",
    "3.0.9",
    "",
    ""
   ]
  },
  {
   "id": "5b9c0df5-9e67-443a-b6e0-7c572b1dbf3f",
   "idx": 106,
   "data": [
    "sufficio odit vesica",
    "KE_URS_17",
    "SRS_107",
    "Suscipit bonus suus aveho ducimus patruus adaugeo.",
    "1.2.2",
    "",
    ""
   ]
  },
  {
   "id": "14e19cba-e929-4261-aaa4-6537f34027b2",
   "idx": 107,
   "data": [
    "vergo degenero succurro",
    "KE_URS_35",
    "SRS_108",
    "Sapiente sublime facilis.",
    "4.2.6",
    "Yes",
    ""
   ]
  },
  {
   "id": "f7ff54c2-e7bc-4292-adbe-f9e22ff3cbe0",
   "idx": 108,
   "data": [
    "comparo aegre corroboro",
    "KE_URS_53",
    "SRS_109",
    "Temporibus confido facere abstergo aiunt tabgo.",
    "3.7.4",
    "",
    ""
   ]
  },
  {
   "id": "1ae5575e-9891-4ad1-ae45-b15b0f548b07",
   "idx": 109,
   "data": [
    "maxime ascisco quasi",
    "KE_URS_78",
    "SRS_110",
    "Utrimque amita virtus sono.",
    "2.2.7",
    "",
    ""
   ]
  },
  {
   "id": "598c2586-5186-4679-a5a0-6a3366179432",
   "idx": 110,
   "data": [
    "cursim denique torrens",
    "KE_URS_65",
    "SRS_111",
    "Curiositas solium supellex sublime vindico magni tracto trucido arx stabilis.",
    "2.8.5",
    "Yes",
    ""
   ]
  },
  {
   "id": "d50f5815-50cd-4c9b-8fa3-b22e372aeaf7",
   "idx": 111,
   "data": [
    "nostrum ulciscor tyrannus",
    "KE_URS_36",
    "SRS_112",
    "Cupio decet tam amitto defluo tactus subito similique ducimus veritatis.",
    "5.7.8",
    "",
    ""
   ]
  },
  {
   "id": "13c20d60-9895-4963-9cbf-c8c5b58f7f77",
   "idx": 112,
   "data": [
    "aliqua crepusculum celer",
    "KE_URS_78",
    "SRS_113",
    "Aer vos curriculum annus temeritas cubitum tener voluptates atrox volup.",
    "4.5.5",
    "Yes",
    ""
   ]
  },
  {
   "id": "0afb5bc4-6d63-4c2a-a9c2-afe930968521",
   "idx": 113,
   "data": [
    "comparo aegre corroboro",
    "KE_URS_76",
    "SRS_114",
    "Animadverto crepusculum textor vulgaris tolero.",
    "5.0.7",
    "",
    ""
   ]
  },
  {
   "id": "7a307253-65a6-4dc7-92ca-6942d26a7afc",
   "idx": 114,
   "data": [
    "depromo accusamus paens",
    "KE_URS_54",
    "SRS_115",
    "Vorax aperte validus canto.",
    "8.9.6",
    "Yes",
    ""
   ]
  },
  {
   "id": "00dc1e41-5cdb-4cfd-b38d-f3507e5da276",
   "idx": 115,
   "data": [
    "aeneus capillus substantia",
    "KE_URS_56",
    "SRS_116",
    "Uberrime deinde porro vito sapiente bonus denego.",
    "7.2.3",
    "",
    ""
   ]
  },
  {
   "id": "8917609a-e8f3-402b-a1c7-0c4951cc4819",
   "idx": 116,
   "data": [
    "sordeo civis trans",
    "KE_URS_81",
    "SRS_117",
    "Subito summisse denique debilito doloribus taceo commodi caelestis.",
    "8.9.6",
    "Yes",
    ""
   ]
  },
  {
   "id": "62529f40-c2fb-4ff2-9d5a-2a30eeb58c18",
   "idx": 117,
   "data": [
    "patruus pecto cuppedia",
    "KE_URS_68",
    "SRS_118",
    "Causa temeritas aegre.",
    "6.1.5",
    "Yes",
    ""
   ]
  },
  {
   "id": "fa147ad9-ba87-4f8c-827a-4c75a196eafc",
   "idx": 118,
   "data": [
    "vulgaris attollo audentia",
    "KE_URS_9",
    "SRS_119",
    "Ipsam absens numquam acervus accusantium xiphias aggero.",
    "2.8.9",
    "Yes",
    ""
   ]
  },
  {
   "id": "d5bc2927-bdc7-45e9-9f70-bb4c769f9f62",
   "idx": 119,
   "data": [
    "angulus beatae voco",
    "KE_URS_56",
    "SRS_120",
    "Terga casso acervus cerno synagoga.",
    "8.3.8",
    "",
    ""
   ]
  },
  {
   "id": "3d4c6d48-84b7-4d18-8d3d-ac5ff4e64085",
   "idx": 120,
   "data": [
    "nostrum ulciscor tyrannus",
    "KE_URS_80",
    "SRS_121",
    "Aequus quas quo nesciunt traho.",
    "8.3.3",
    "Yes",
    ""
   ]
  },
  {
   "id": "371b5b84-145d-4b94-8a28-6d2f796627cd",
   "idx": 121,
   "data": [
    "talis tui solitudo",
    "KE_URS_37",
    "SRS_122",
    "Cupressus civitas vespillo degenero praesentium campana ancilla.",
    "5.5.9",
    "Yes",
    ""
   ]
  },
  {
   "id": "4fc1e911-4453-4ae3-87c5-522b9e51b371",
   "idx": 122,
   "data": [
    "cursim denique torrens",
    "KE_URS_87",
    "SRS_123",
    "Cognatus stabilis annus.",
    "6.5.6",
    "",
    ""
   ]
  },
  {
   "id": "2798284f-b9fe-40fc-a17c-c27789599801",
   "idx": 123,
   "data": [
    "consuasor audentia ab",
    "KE_URS_63",
    "SRS_124",
    "Abbas benigne conqueror.",
    "1.4.2",
    "Yes",
    "N/A"
   ]
  },
  {
   "id": "647f5515-b116-4c92-bcd8-bd5ed6e139c6",
   "idx": 124,
   "data": [
    "cogo a terra",
    "KE_URS_33",
    "SRS_125",
    "Accendo cras valens.",
    "5.1.3",
    "",
    ""
   ]
  },
  {
   "id": "59b2ad9e-815c-4646-b79d-daa5048b6d69",
   "idx": 125,
   "data": [
    "depromo accusamus paens",
    "KE_URS_50",
    "SRS_126",
    "Celo colo caute minus amitto officiis corona aggredior sperno virga.",
    "2.8.4",
    "",
    ""
   ]
  },
  {
   "id": "a5f77d6d-b6ef-44be-b161-82d7769c81bc",
   "idx": 126,
   "data": [
    "talis tui solitudo",
    "KE_URS_39",
    "SRS_127",
    "Synagoga usque antea tergo cohibeo vado comis possimus.",
    "6.0.2",
    "Yes",
    ""
   ]
  },
  {
   "id": "24a4ae76-6b2d-4b78-b4fa-85755088b902",
   "idx": 127,
   "data": [
    "aliqua crepusculum celer",
    "KE_URS_19",
    "SRS_128",
    "Crapula comburo aufero et delectus bellum solus.",
    "4.3.0",
    "",
    "N/A"
   ]
  },
  {
   "id": "75d7bdd3-a2aa-4816-a38e-5588568b1c80",
   "idx": 128,
   "data": [
    "vis aggredior capto",
    "KE_URS_31",
    "SRS_129",
    "Paulatim surculus excepturi adfero animadverto celer sodalitas allatus.",
    "7.9.7",
    "Yes",
    ""
   ]
  },
  {
   "id": "ee000dc6-c160-4dd4-a0a5-36ffbd4c2390",
   "idx": 129,
   "data": [
    "angulus beatae voco",
    "KE_URS_75",
    "SRS_130",
    "Dens sapiente beneficium cariosus.",
    "0.6.9",
    "Yes",
    ""
   ]
  },
  {
   "id": "e170b924-714b-4c44-9846-cefe1eb31bfc",
   "idx": 130,
   "data": [
    "somnus ratione valde",
    "KE_URS_67",
    "SRS_131",
    "Crux quia decerno speciosus.",
    "7.9.9",
    "Yes",
    ""
   ]
  },
  {
   "id": "a10709ad-d596-4aa8-a2e2-c1dee100161c",
   "idx": 131,
   "data": [
    "vacuus nostrum doloribus",
    "KE_URS_39",
    "SRS_132",
    "Spero spargo celebrer voco valens.",
    "0.6.0",
    "Yes",
    "N/A"
   ]
  },
  {
   "id": "6ed637fa-537e-452b-aee5-b1817182f728",
   "idx": 132,
   "data": [
    "sordeo civis trans",
    "KE_URS_45",
    "SRS_133",
    "Suscipit laboriosam creber.",
    "3.5.8",
    "Yes",
    ""
   ]
  },
  {
   "id": "82a99e0f-1d04-447e-bbfc-1b88ac670c7a",
   "idx": 133,
   "data": [
    "vestrum vicinus tabgo",
    "KE_URS_23",
    "SRS_134",
    "Denuo facilis admitto adimpleo.",
    "3.7.6",
    "Yes",
    ""
   ]
  },
  {
   "id": "55d612c1-0b0d-44ab-8d66-23e12295842e",
   "idx": 134,
   "data": [
    "aliqua crepusculum celer",
    "KE_URS_7",
    "SRS_135",
    "Credo adflicto benevolentia cunae abundans aufero ter deleniti tabgo.",
    "1.7.7",
    "Yes",
    ""
   ]
  },
  {
   "id": "5ac91149-f1fe-480e-bb04-903c97205bb9",
   "idx": 135,
   "data": [
    "cogo a terra",
    "KE_URS_58",
    "SRS_136",
    "Comes speciosus soluta copiose tubineus infit approbo barba.",
    "8.9.0",
    "Yes",
    ""
   ]
  },
  {
   "id": "2c23eb1b-62ec-48ec-8c2f-45a6b2b3d02e",
   "idx": 136,
   "data": [
    "vulgaris attollo audentia",
    "KE_URS_12",
    "SRS_137",
    "Adversus urbs labore dedico tibi.",
    "1.8.8",
    "Yes",
    ""
   ]
  },
  {
   "id": "355e6f47-cd40-49c4-b112-447a7659be99",
   "idx": 137,
   "data": [
    "vergo degenero succurro",
    "KE_URS_97",
    "SRS_138",
    "Tibi capto cibo tabesco comburo iure fugiat deprimo stella clementia.",
    "5.4.9",
    "",
    ""
   ]
  },
  {
   "id": "6538cc27-6cb3-417d-b3c0-a444f23da630",
   "idx": 138,
   "data": [
    "cogo a terra",
    "KE_URS_79",
    "SRS_139",
    "Ubi vinitor bis tumultus adhuc taedium.",
    "0.0.8",
    "",
    ""
   ]
  },
  {
   "id": "c141eef6-5aa1-4af9-9641-790d053e6dfa",
   "idx": 139,
   "data": [
    "maxime ascisco quasi",
    "KE_URS_99",
    "SRS_140",
    "Acquiro confugo explicabo sufficio.",
    "8.2.6",
    "Yes",
    ""
   ]
  },
  {
   "id": "d901a218-e5d8-4202-98e0-fd64298be1fc",
   "idx": 140,
   "data": [
    "somnus ratione valde",
    "KE_URS_34",
    "SRS_141",
    "Vix sit cogo comedo deduco tabgo taceo.",
    "4.4.5",
    "Yes",
    "N/A"
   ]
  },
  {
   "id": "c9df0554-f6f1-4f8a-812c-796d1061634f",
   "idx": 141,
   "data": [
    "consuasor audentia ab",
    "KE_URS_90",
    "SRS_142",
    "Thermae illo ars autem arbitro utor nemo.",
    "6.3.3",
    "Yes",
    ""
   ]
  },
  {
   "id": "9a6566cd-1720-4303-8366-3f034c8af433",
   "idx": 142,
   "data": [
    "conscendo una toties",
    "KE_URS_16",
    "SRS_143",
    "Cauda ab reprehenderit videlicet debilito aliquid.",
    "3.6.8",
    "Yes",
    ""
   ]
  },
  {
   "id": "c65dbc74-0a60-4c98-ae01-349ade81aeb4",
   "idx": 143,
   "data": [
    "ducimus doloribus damnatio",
    "KE_URS_64",
    "SRS_144",
    "Apparatus absum chirographum.",
    "0.9.8",
    "Yes",
    ""
   ]
  },
  {
   "id": "89e515cf-e628-4ec0-8023-7cc8a5594c74",
   "idx": 144,
   "data": [
    "talis tui solitudo",
    "KE_URS_49",
    "SRS_145",
    "Antiquus depromo ceno congregatio acsi audio vulgus stultus.",
    "5.7.9",
    "Yes",
    ""
   ]
  },
  {
   "id": "ad04ac17-4785-4710-965a-b7b477e7aa8a",
   "idx": 145,
   "data": [
    "comparo aegre corroboro",
    "KE_URS_93",
    "SRS_146",
    "Recusandae uterque adsuesco utique sortitus colligo.",
    "1.8.3",
    "Yes",
    ""
   ]
  },
  {
   "id": "5f933de0-36c5-461a-b8a5-4d286616b047",
   "idx": 146,
   "data": [
    "aliqua crepusculum celer",
    "KE_URS_81",
    "SRS_147",
    "Aiunt coepi clam comptus soleo.",
    "1.9.7",
    "",
    ""
   ]
  },
  {
   "id": "b1abd129-40cf-42e1-af37-151cf9353915",
   "idx": 147,
   "data": [
    "cogo a terra",
    "KE_URS_85",
    "SRS_148",
    "Audax contra caries virtus correptius tergeo cruciamentum vulnus vallum comprehendo.",
    "1.1.8",
    "",
    ""
   ]
  },
  {
   "id": "53b23910-d7ff-4d51-ac2f-d041a06277fd",
   "idx": 148,
   "data": [
    "sordeo civis trans",
    "KE_URS_56",
    "SRS_149",
    "Villa curto pecus defluo claustrum theologus.",
    "2.4.6",
    "Yes",
    ""
   ]
  },
  {
   "id": "48e9e623-4607-445c-b32a-8a53a99c7f46",
   "idx": 149,
   "data": [
    "somnus ratione valde",
    "KE_URS_24",
    "SRS_150",
    "Curriculum tardus attero est.",
    "3.7.7",
    "Yes",
    "N/A"
   ]
  },
  {
   "id": "4fecc25a-f291-4f2a-952a-3c1d31335de0",
   "idx": 150,
   "data": [
    "ducimus doloribus damnatio",
    "KE_URS_56",
    "SRS_151",
    "Uredo varietas amo cometes xiphias alioqui thorax vobis et apparatus.",
    "4.9.3",
    "Yes",
    ""
   ]
  },
  {
   "id": "6aefc7f9-f1a7-4aae-9c2a-015f3683221c",
   "idx": 151,
   "data": [
    "patruus pecto cuppedia",
    "KE_URS_30",
    "SRS_152",
    "Confido adaugeo tracto textor.",
    "9.4.4",
    "",
    ""
   ]
  },
  {
   "id": "4c613dc6-e85d-4639-b4f9-8b93fe7e4ceb",
   "idx": 152,
   "data": [
    "adopto demoror sint",
    "KE_URS_34",
    "SRS_153",
    "Canis sapiente trado vallum taceo cado correptius concido complectus.",
    "9.2.1",
    "Yes",
    ""
   ]
  },
  {
   "id": "2ed6ae5a-07ba-480f-8587-421d31d29cde",
   "idx": 153,
   "data": [
    "depromo accusamus paens",
    "KE_URS_40",
    "SRS_154",
    "Acquiro unus absens unus careo.",
    "6.5.0",
    "Yes",
    ""
   ]
  },
  {
   "id": "02e72d79-b83e-4a87-a8fe-15cd9c28285f",
   "idx": 154,
   "data": [
    "vis aggredior capto",
    "KE_URS_28",
    "SRS_155",
    "Officiis vita adnuo ventito sopor advenio cimentarius.",
    "7.6.5",
    "",
    ""
   ]
  },
  {
   "id": "850f4e85-488d-477b-9ddf-6da5b68c8154",
   "idx": 155,
   "data": [
    "ducimus doloribus damnatio",
    "KE_URS_97",
    "SRS_156",
    "Territo verecundia sustineo crapula adopto cursus aedificium statim.",
    "7.5.2",
    "Yes",
    ""
   ]
  },
  {
   "id": "812abd30-1d42-498d-b3d6-064972d4f7e2",
   "idx": 156,
   "data": [
    "vergo degenero succurro",
    "KE_URS_41",
    "SRS_157",
    "Delibero capitulus demens amplus amitto maiores cursim benevolentia vester aggredior.",
    "6.4.8",
    "Yes",
    ""
   ]
  },
  {
   "id": "fafd8ef8-9550-4e4c-9f55-ed617b73f736",
   "idx": 157,
   "data": [
    "bos baiulus surgo",
    "KE_URS_87",
    "SRS_158",
    "Denuncio atrocitas similique.",
    "2.5.3",
    "",
    "N/A"
   ]
  },
  {
   "id": "4432691f-c4a4-4f12-be4f-d947bf988f21",
   "idx": 158,
   "data": [
    "ustilo creo crebro",
    "KE_URS_85",
    "SRS_159",
    "Dicta ipsa amor vita crux.",
    "7.6.2",
    "Yes",
    ""
   ]
  },
  {
   "id": "07dac7c5-8cb0-494e-93c8-670a5f55c746",
   "idx": 159,
   "data": [
    "comparo aegre corroboro",
    "KE_URS_65",
    "SRS_160",
    "Repellat comes admoveo amicitia volaticus vilicus benevolentia degero attero uter.",
    "0.3.1",
    "Yes",
    ""
   ]
  },
  {
   "id": "33129912-6cc7-4850-84f2-e03c79956618",
   "idx": 160,
   "data": [
    "depromo accusamus paens",
    "KE_URS_66",
    "SRS_161",
    "Aeternus terror vomica clementia vado abscido.",
    "0.6.1",
    "Yes",
    ""
   ]
  },
  {
   "id": "93fccb27-0560-4b88-aee3-6257ed837307",
   "idx": 161,
   "data": [
    "aliquam coadunatio abutor",
    "KE_URS_97",
    "SRS_162",
    "Vae ducimus aegrotatio dolorum quidem comburo thalassinus.",
    "0.6.7",
    "",
    ""
   ]
  },
  {
   "id": "bd2fca34-0da8-4f0b-9f05-ca679683cda1",
   "idx": 162,
   "data": [
    "conscendo una toties",
    "KE_URS_99",
    "SRS_163",
    "Comis caelestis sed accommodo.",
    "4.3.1",
    "",
    ""
   ]
  },
  {
   "id": "7d3635e4-9b3b-499f-b1db-e2625e9463b9",
   "idx": 163,
   "data": [
    "consuasor audentia ab",
    "KE_URS_40",
    "SRS_164",
    "Praesentium coepi solium triduana abutor.",
    "9.3.0",
    "Yes",
    ""
   ]
  },
  {
   "id": "344fde83-4e84-44d5-94fe-7e2e181bfa93",
   "idx": 164,
   "data": [
    "vacuus nostrum doloribus",
    "KE_URS_9",
    "SRS_165",
    "Velut defetiscor cotidie venustas aequus porro bestia aspicio arceo beatae.",
    "0.4.9",
    "Yes",
    ""
   ]
  },
  {
   "id": "f1a88223-9621-4c37-8f24-09b30e817617",
   "idx": 165,
   "data": [
    "maxime ascisco quasi",
    "KE_URS_76",
    "SRS_166",
    "Cur enim tabgo tergeo suppono amicitia tracto.",
    "6.3.9",
    "",
    "N/A"
   ]
  },
  {
   "id": "8545105e-d649-4a94-b119-f1a703ced2da",
   "idx": 166,
   "data": [
    "ducimus doloribus damnatio",
    "KE_URS_8",
    "SRS_167",
    "Vinitor animus arbustum sollers turba laboriosam comminor desparatus.",
    "9.5.3",
    "Yes",
    ""
   ]
  },
  {
   "id": "219dcd73-f3a8-4f82-a3b3-60b4bb13162a",
   "idx": 167,
   "data": [
    "cursim denique torrens",
    "KE_URS_28",
    "SRS_168",
    "Nisi vacuus placeat vestigium tutamen at dignissimos.",
    "3.7.2",
    "Yes",
    ""
   ]
  },
  {
   "id": "6180daf2-1b28-491d-b5d9-ee518d04cadd",
   "idx": 168,
   "data": [
    "ustilo creo crebro",
    "KE_URS_42",
    "SRS_169",
    "Contabesco cursus agnosco consequatur patrocinor aut ustilo aufero tui deficio.",
    "1.4.9",
    "Yes",
    ""
   ]
  },
  {
   "id": "20643847-f376-437d-88f3-c455ba26184a",
   "idx": 169,
   "data": [
    "cursim denique torrens",
    "KE_URS_62",
    "SRS_170",
    "Tabernus cibo damno aegrus vir repellendus conscendo ater.",
    "3.3.5",
    "Yes",
    ""
   ]
  },
  {
   "id": "d76d12e3-baa3-45c5-b37e-c2cfc428441a",
   "idx": 170,
   "data": [
    "vergo degenero succurro",
    "KE_URS_91",
    "SRS_171",
    "Abbas summisse commemoro taceo accusamus dicta curriculum tergo occaecati.",
    "4.9.9",
    "",
    ""
   ]
  },
  {
   "id": "9f15f451-75c4-4e1b-a68a-b89b1bf46794",
   "idx": 171,
   "data": [
    "vulgaris attollo audentia",
    "KE_URS_64",
    "SRS_172",
    "Tandem substantia nostrum trado demo spiritus curvo taceo demo subito.",
    "5.0.5",
    "Yes",
    ""
   ]
  },
  {
   "id": "04c500d5-8f6f-4ee2-b38b-1c0a2ee7b434",
   "idx": 172,
   "data": [
    "vis aggredior capto",
    "KE_URS_83",
    "SRS_173",
    "Suspendo totidem apostolus paulatim.",
    "7.5.5",
    "",
    ""
   ]
  },
  {
   "id": "ff686261-dd73-44db-9ee6-c6d3dd74d22e",
   "idx": 173,
   "data": [
    "bos baiulus surgo",
    "KE_URS_10",
    "SRS_174",
    "Cumque eum uter caritas arma comptus earum.",
    "5.2.3",
    "Yes",
    ""
   ]
  },
  {
   "id": "f258d7a0-7fd5-47a3-a4cf-0eb3563494cf",
   "idx": 174,
   "data": [
    "maxime ascisco quasi",
    "KE_URS_54",
    "SRS_175",
    "Vitium aspernatur ascisco ab.",
    "5.6.8",
    "",
    ""
   ]
  },
  {
   "id": "4ebe2523-8bcb-4ec1-9287-63bfb090e518",
   "idx": 175,
   "data": [
    "vergo degenero succurro",
    "KE_URS_86",
    "SRS_176",
    "Bibo fugiat arbor conicio repudiandae.",
    "9.4.0",
    "Yes",
    ""
   ]
  },
  {
   "id": "2b232c1b-d904-444b-947f-8dfaf6cafa41",
   "idx": 176,
   "data": [
    "varietas utrimque bellum",
    "KE_URS_32",
    "SRS_177",
    "Pax tenax cerno comparo vulgaris harum aequitas debilito ante terror.",
    "8.7.0",
    "",
    "N/A"
   ]
  },
  {
   "id": "b894b11f-a8ad-4559-84a3-4c96e869fc90",
   "idx": 177,
   "data": [
    "comparo aegre corroboro",
    "KE_URS_75",
    "SRS_178",
    "Comminor non porro ventosus angulus appono super tenetur cursus.",
    "0.1.6",
    "",
    ""
   ]
  },
  {
   "id": "dd11338a-ef8d-4192-a8d5-dc6b2246b532",
   "idx": 178,
   "data": [
    "tamquam abeo usus",
    "KE_URS_83",
    "SRS_179",
    "Quo eos crux tunc clamo.",
    "5.0.2",
    "",
    ""
   ]
  },
  {
   "id": "3dbf87b3-7a32-4f4f-a464-9fabca49f3f0",
   "idx": 179,
   "data": [
    "ustilo creo crebro",
    "KE_URS_75",
    "SRS_180",
    "Patrocinor tener depopulo corroboro delego tametsi.",
    "3.9.5",
    "Yes",
    ""
   ]
  },
  {
   "id": "739241e7-28a1-4302-a552-022c5d5e0150",
   "idx": 180,
   "data": [
    "arcus assentator assentator",
    "KE_URS_19",
    "SRS_181",
    "Derideo spiritus voveo dolores necessitatibus ocer cogo debeo cunae campana.",
    "4.1.2",
    "",
    ""
   ]
  },
  {
   "id": "f09d3f0d-43dd-4f1a-aace-9a925296926d",
   "idx": 181,
   "data": [
    "veritas tabesco delibero",
    "KE_URS_95",
    "SRS_182",
    "Decens tametsi viscus copia atrocitas.",
    "0.2.1",
    "",
    ""
   ]
  },
  {
   "id": "f2497285-577d-4de5-8779-25ae8debe885",
   "idx": 182,
   "data": [
    "vulgaris attollo audentia",
    "KE_URS_67",
    "SRS_183",
    "Ea vesica suus corrumpo summisse viscus tolero ventosus vociferor.",
    "5.6.2",
    "Yes",
    ""
   ]
  },
  {
   "id": "8ac4b7f4-4f96-415d-8f25-ac8d028cc15c",
   "idx": 183,
   "data": [
    "basium textus verbum",
    "KE_URS_69",
    "SRS_184",
    "Dedico chirographum quam thermae tabesco aurum sumo ultra ter aut.",
    "4.6.1",
    "Yes",
    ""
   ]
  },
  {
   "id": "35ac64be-3979-4320-99e0-d756e0dff47a",
   "idx": 184,
   "data": [
    "maxime ascisco quasi",
    "KE_URS_40",
    "SRS_185",
    "Spiritus appositus vae crinis cupio crepusculum harum utique.",
    "1.3.4",
    "Yes",
    ""
   ]
  },
  {
   "id": "a27f4604-a1c3-43a1-99be-406f3bb90be9",
   "idx": 185,
   "data": [
    "aeneus capillus substantia",
    "KE_URS_65",
    "SRS_186",
    "Vigor collum vel suppono voluptate coniuratio aliqua adicio volubilis.",
    "4.7.0",
    "Yes",
    ""
   ]
  },
  {
   "id": "18a79330-f981-4515-85b8-444111ca5fc1",
   "idx": 186,
   "data": [
    "vergo degenero succurro",
    "KE_URS_91",
    "SRS_187",
    "Creber conitor solvo combibo adeo cubo spes taceo.",
    "5.5.2",
    "Yes",
    ""
   ]
  },
  {
   "id": "a19fa4b8-6d70-4bce-a06e-fd68f61caa44",
   "idx": 187,
   "data": [
    "patruus pecto cuppedia",
    "KE_URS_82",
    "SRS_188",
    "Comparo traho avarus carmen.",
    "1.5.0",
    "Yes",
    ""
   ]
  },
  {
   "id": "b96eb50f-0000-4022-b05a-cca3a13a5295",
   "idx": 188,
   "data": [
    "bos baiulus surgo",
    "KE_URS_41",
    "SRS_189",
    "Aveho spes sol corona ducimus testimonium vulgus eveniet.",
    "8.0.8",
    "",
    ""
   ]
  },
  {
   "id": "b8d7196f-9c3d-4d99-8e2a-221a0f803ed7",
   "idx": 189,
   "data": [
    "arcus assentator assentator",
    "KE_URS_80",
    "SRS_190",
    "Desidero arcesso animadverto cavus solitudo patrocinor certe.",
    "9.8.9",
    "Yes",
    ""
   ]
  },
  {
   "id": "9862eb1a-061c-451a-ba52-6609aa9b7969",
   "idx": 190,
   "data": [
    "sufficio odit vesica",
    "KE_URS_73",
    "SRS_191",
    "Ancilla pax apto asporto urbanus tabgo civis copiose nostrum.",
    "7.0.7",
    "Yes",
    ""
   ]
  },
  {
   "id": "46d870ef-4084-443f-b759-c2ba78bed1a4",
   "idx": 191,
   "data": [
    "cursim denique torrens",
    "KE_URS_29",
    "SRS_192",
    "Defluo vix accusantium.",
    "1.4.5",
    "Yes",
    ""
   ]
  },
  {
   "id": "5c353644-cb47-486c-981e-76ff1c22f144",
   "idx": 192,
   "data": [
    "aliqua crepusculum celer",
    "KE_URS_61",
    "SRS_193",
    "Conscendo tero cunabula via nobis tergeo aiunt.",
    "4.3.7",
    "Yes",
    ""
   ]
  },
  {
   "id": "7656300a-c9cf-4b37-a372-28e3c2c53902",
   "idx": 193,
   "data": [
    "varietas utrimque bellum",
    "KE_URS_6",
    "SRS_194",
    "Trado cruciamentum deporto curiositas inventore confido derelinquo tabesco vetus tertius.",
    "0.9.2",
    "Yes",
    ""
   ]
  },
  {
   "id": "af0f263f-2750-4279-9bb1-769633f8ed78",
   "idx": 194,
   "data": [
    "bos baiulus surgo",
    "KE_URS_32",
    "SRS_195",
    "Abbas arbitro thesis vinitor ante cena cruentus.",
    "8.1.0",
    "Yes",
    ""
   ]
  },
  {
   "id": "4baeb942-8624-4db1-ab8c-1f177612c05c",
   "idx": 195,
   "data": [
    "antepono aestivus tabgo",
    "KE_URS_33",
    "SRS_196",
    "Adficio claustrum aro ipsa tempora.",
    "9.1.9",
    "",
    ""
   ]
  },
  {
   "id": "f3c29a9f-3920-4449-96e3-c30329952e24",
   "idx": 196,
   "data": [
    "vacuus nostrum doloribus",
    "KE_URS_89",
    "SRS_197",
    "Ducimus absorbeo causa aptus tepesco desparatus.",
    "2.4.0",
    "Yes",
    ""
   ]
  },
  {
   "id": "09342be7-2791-4be5-9b7a-c1a4f8c7a427",
   "idx": 197,
   "data": [
    "vergo degenero succurro",
    "KE_URS_67",
    "SRS_198",
    "Colo aegre compono molestias ago agnitio cognatus aedificium.",
    "5.6.7",
    "",
    ""
   ]
  },
  {
   "id": "395a06b8-0045-4c2e-81f3-eaf4bc6a5afd",
   "idx": 198,
   "data": [
    "cursim denique torrens",
    "KE_URS_27",
    "SRS_199",
    "Agnitio substantia desipio thesaurus caute toties ulterius.",
    "8.5.4",
    "Yes",
    ""
   ]
  },
  {
   "id": "00df7b8f-db82-472d-9301-4487bff5f74d",
   "idx": 199,
   "data": [
    "cogo a terra",
    "KE_URS_19",
    "SRS_200",
    "Coadunatio delectus utique ciminatio.",
    "7.6.5",
    "Yes",
    ""
   ]
  },
  {
   "id": "bb9f5e4d-bf89-4859-9cd3-346dfb802e95",
   "idx": 200,
   "data": [
    "tamquam abeo usus",
    "KE_URS_79",
    "SRS_201",
    "Traho minima artificiose in decretum creptio tenus textilis aeternus officiis.",
    "2.9.9",
    "Yes",
    ""
   ]
  },
  {
   "id": "e61aa52b-54ca-41c8-b402-54b929e0599f",
   "idx": 201,
   "data": [
    "bos baiulus surgo",
    "KE_URS_9",
    "SRS_202",
    "Cumque temporibus deripio turpis tempora cum bis valde venia adimpleo.",
    "6.4.5",
    "Yes",
    "N/A"
   ]
  },
  {
   "id": "259d90ae-c617-45ab-86dc-b97ba82db233",
   "idx": 202,
   "data": [
    "vulgaris attollo audentia",
    "KE_URS_57",
    "SRS_203",
    "Ulterius id suasoria ullus vaco chirographum.",
    "1.8.6",
    "",
    ""
   ]
  },
  {
   "id": "02469c04-b98f-47c6-80dc-bd3fa989acf6",
   "idx": 203,
   "data": [
    "bos baiulus surgo",
    "KE_URS_23",
    "SRS_204",
    "Temperantia speciosus trans creber cervus.",
    "0.5.2",
    "",
    "N/A"
   ]
  },
  {
   "id": "3107ea00-241a-4e4c-b6a0-5beab4ba80b6",
   "idx": 204,
   "data": [
    "arcus assentator assentator",
    "KE_URS_77",
    "SRS_205",
    "Ducimus aetas quasi sophismata vinum aurum.",
    "6.1.6",
    "Yes",
    ""
   ]
  },
  {
   "id": "18901463-f269-490f-801d-e7957d77947d",
   "idx": 205,
   "data": [
    "consuasor audentia ab",
    "KE_URS_82",
    "SRS_206",
    "Acervus vulgivagus voro.",
    "6.9.3",
    "Yes",
    ""
   ]
  },
  {
   "id": "26650266-c43f-41f0-9d87-72beba97faea",
   "idx": 206,
   "data": [
    "claudeo volva turba",
    "KE_URS_7",
    "SRS_207",
    "Agnitio amplus campana summopere sunt adsum.",
    "3.8.4",
    "",
    ""
   ]
  },
  {
   "id": "9f5f45c7-7794-4799-894e-ef77cdeba844",
   "idx": 207,
   "data": [
    "nostrum ulciscor tyrannus",
    "KE_URS_80",
    "SRS_208",
    "Suadeo arca vinum iure conforto caput tristis auditor alveus vigor.",
    "2.1.7",
    "Yes",
    ""
   ]
  },
  {
   "id": "ae9fd881-1e9b-4055-90e7-69acee51fad0",
   "idx": 208,
   "data": [
    "vergo degenero succurro",
    "KE_URS_56",
    "SRS_209",
    "Adsum debilito iusto defleo convoco villa quae derelinquo contabesco surculus.",
    "2.3.7",
    "",
    "N/A"
   ]
  },
  {
   "id": "3ef963e0-c5c1-442d-bec4-da979e373c39",
   "idx": 209,
   "data": [
    "talis tui solitudo",
    "KE_URS_57",
    "SRS_210",
    "Constans eius temperantia thymbra cohibeo spes abstergo.",
    "7.6.6",
    "",
    ""
   ]
  },
  {
   "id": "eb70784d-80d2-4351-ad26-1293aa9295fd",
   "idx": 210,
   "data": [
    "tamquam abeo usus",
    "KE_URS_27",
    "SRS_211",
    "Adeo totidem voluptate texo tamdiu verumtamen corrupti venustas claro communis.",
    "8.4.6",
    "",
    ""
   ]
  },
  {
   "id": "339741f0-569a-492b-a787-457b897f4749",
   "idx": 211,
   "data": [
    "adopto demoror sint",
    "KE_URS_96",
    "SRS_212",
    "Textilis usitas aptus.",
    "2.2.6",
    "",
    ""
   ]
  },
  {
   "id": "fce33489-ad7c-48dc-ac85-0e8580a181d8",
   "idx": 212,
   "data": [
    "veritas tabesco delibero",
    "KE_URS_36",
    "SRS_213",
    "Depopulo auxilium crinis culpo tabernus articulus vigor.",
    "3.7.3",
    "Yes",
    ""
   ]
  },
  {
   "id": "8669b5af-4204-476f-a6a0-3a6a55fa171e",
   "idx": 213,
   "data": [
    "patruus pecto cuppedia",
    "KE_URS_40",
    "SRS_214",
    "In qui circumvenio commodo aufero.",
    "8.2.8",
    "Yes",
    ""
   ]
  },
  {
   "id": "51d16c9b-3417-4502-b7b0-93723fbbeca2",
   "idx": 214,
   "data": [
    "talis tui solitudo",
    "KE_URS_23",
    "SRS_215",
    "Administratio aspicio amor cursus vulticulus barba attero.",
    "7.6.3",
    "",
    ""
   ]
  },
  {
   "id": "eff70016-9086-4cca-85b4-e35105bd24a0",
   "idx": 215,
   "data": [
    "varietas utrimque bellum",
    "KE_URS_23",
    "SRS_216",
    "Socius velum curia capio ubi terra corrupti defendo subvenio adimpleo.",
    "9.9.7",
    "",
    ""
   ]
  },
  {
   "id": "b1c9592a-7ac1-4652-b524-53ebe95c4032",
   "idx": 216,
   "data": [
    "vulgaris attollo audentia",
    "KE_URS_47",
    "SRS_217",
    "Terra bonus comparo tutamen textilis capto curtus.",
    "2.4.7",
    "",
    ""
   ]
  },
  {
   "id": "77b65bcf-0e79-406d-9d47-9a9ccc889453",
   "idx": 217,
   "data": [
    "tamquam abeo usus",
    "KE_URS_17",
    "SRS_218",
    "Solvo defaeco magni.",
    "2.5.8",
    "",
    ""
   ]
  },
  {
   "id": "55ebb809-2429-4c24-bdf2-6e699cbcdfa8",
   "idx": 218,
   "data": [
    "consuasor audentia ab",
    "KE_URS_9",
    "SRS_219",
    "Cetera summisse cras vere conturbo utrum bene ait sophismata.",
    "9.1.6",
    "Yes",
    ""
   ]
  },
  {
   "id": "a0d02a5c-c76d-4bd3-8067-e396469fe51c",
   "idx": 219,
   "data": [
    "depromo accusamus paens",
    "KE_URS_8",
    "SRS_220",
    "Similique audacia tepesco ustilo quaerat aliquid unus claustrum teres aequitas.",
    "9.3.9",
    "",
    ""
   ]
  },
  {
   "id": "99a3ac8b-b7cf-4b2c-98c8-0878c40e6c33",
   "idx": 220,
   "data": [
    "sufficio odit vesica",
    "KE_URS_44",
    "SRS_221",
    "Absque theca timidus commodi cubo casso clarus deinde incidunt allatus.",
    "3.9.3",
    "Yes",
    ""
   ]
  },
  {
   "id": "49031a70-7900-443e-b254-7b7f88336980",
   "idx": 221,
   "data": [
    "basium textus verbum",
    "KE_URS_67",
    "SRS_222",
    "Audio praesentium acerbitas.",
    "7.4.6",
    "Yes",
    ""
   ]
  },
  {
   "id": "b8d5364a-1ad7-49f1-84bf-f0fe3642e3b0",
   "idx": 222,
   "data": [
    "cogo a terra",
    "KE_URS_52",
    "SRS_223",
    "Deinde crinis articulus veritas voco vesco vulnero vir.",
    "3.6.7",
    "Yes",
    ""
   ]
  },
  {
   "id": "f69563b2-4b20-42a8-afdb-041e0acc1387",
   "idx": 223,
   "data": [
    "perferendis talis culpa",
    "KE_URS_75",
    "SRS_224",
    "Volva solus cunctatio benevolentia.",
    "4.9.7",
    "Yes",
    ""
   ]
  },
  {
   "id": "33fd3472-f185-49e3-9e0b-4bb10cb71f7d",
   "idx": 224,
   "data": [
    "aliquam coadunatio abutor",
    "KE_URS_71",
    "SRS_225",
    "Vester viriliter temeritas.",
    "6.6.5",
    "",
    ""
   ]
  },
  {
   "id": "a22e3068-2c6c-4749-ba50-ec11d7b66200",
   "idx": 225,
   "data": [
    "vacuus nostrum doloribus",
    "KE_URS_9",
    "SRS_226",
    "Aedificium theologus veniam timidus culpo acies vinco uxor vitium.",
    "0.2.8",
    "Yes",
    ""
   ]
  },
  {
   "id": "6ac5a749-c6eb-454d-abc5-6275cf5b01a5",
   "idx": 226,
   "data": [
    "veritas tabesco delibero",
    "KE_URS_68",
    "SRS_227",
    "Ventito debitis cupio tubineus averto apto universe cui suscipit.",
    "6.0.8",
    "",
    ""
   ]
  },
  {
   "id": "5621ed4c-bf9b-4282-9e5d-5f23f0eada62",
   "idx": 227,
   "data": [
    "aeneus capillus substantia",
    "KE_URS_37",
    "SRS_228",
    "Adicio casso bis comes cariosus ultio nulla theologus abeo crapula.",
    "4.1.9",
    "Yes",
    ""
   ]
  },
  {
   "id": "3913fd22-623b-400f-9ced-9e738e00a4a3",
   "idx": 228,
   "data": [
    "vis aggredior capto",
    "KE_URS_26",
    "SRS_229",
    "Itaque provident conculco varietas ulterius nobis valde somniculosus.",
    "5.2.9",
    "Yes",
    ""
   ]
  },
  {
   "id": "98527a69-2cc3-4eba-a03c-d1bd3c389775",
   "idx": 229,
   "data": [
    "sufficio odit vesica",
    "KE_URS_95",
    "SRS_230",
    "Assentator textus expedita pel una venia curriculum.",
    "5.9.2",
    "Yes",
    ""
   ]
  },
  {
   "id": "57003585-affd-43a9-95bb-79fb397e6ab7",
   "idx": 230,
   "data": [
    "antepono aestivus tabgo",
    "KE_URS_63",
    "SRS_231",
    "Spiculum accusamus credo perspiciatis deludo.",
    "8.9.7",
    "",
    ""
   ]
  },
  {
   "id": "b31b0990-41a1-443a-a890-e340b7c56614",
   "idx": 231,
   "data": [
    "basium textus verbum",
    "KE_URS_32",
    "SRS_232",
    "Summisse chirographum civis.",
    "2.8.8",
    "",
    ""
   ]
  },
  {
   "id": "e4e9c4e1-6706-4bbb-b088-9756fd6603b6",
   "idx": 232,
   "data": [
    "vestrum vicinus tabgo",
    "KE_URS_80",
    "SRS_233",
    "Amor spoliatio aut compello id alioqui titulus.",
    "0.8.9",
    "",
    ""
   ]
  },
  {
   "id": "3efe9bd9-d806-42fc-a641-6519e4022588",
   "idx": 233,
   "data": [
    "aliquam coadunatio abutor",
    "KE_URS_48",
    "SRS_234",
    "Sed desparatus comptus.",
    "3.7.5",
    "Yes",
    ""
   ]
  },
  {
   "id": "5a47b936-5558-48d0-811c-7afbd1329019",
   "idx": 234,
   "data": [
    "angulus beatae voco",
    "KE_URS_90",
    "SRS_235",
    "Vetus amplitudo hic provident tutis campana cohibeo vesper.",
    "9.8.5",
    "",
    ""
   ]
  },
  {
   "id": "31572be2-728d-42a0-9435-d27d96d1c423",
   "idx": 235,
   "data": [
    "sordeo civis trans",
    "KE_URS_77",
    "SRS_236",
    "Tumultus apud aranea sulum vel atqui valens animus virga aedificium.",
    "5.8.0",
    "Yes",
    ""
   ]
  },
  {
   "id": "6d582191-d1e9-4e47-a456-22d9249243ba",
   "idx": 236,
   "data": [
    "bos baiulus surgo",
    "KE_URS_61",
    "SRS_237",
    "Clarus quos comprehendo caput.",
    "1.5.0",
    "",
    ""
   ]
  },
  {
   "id": "1c233380-470c-4d8c-bc3a-f70659f43eee",
   "idx": 237,
   "data": [
    "veritas tabesco delibero",
    "KE_URS_89",
    "SRS_238",
    "Creta cultura chirographum denuncio laboriosam quos deleo antea.",
    "5.9.7",
    "Yes",
    ""
   ]
  },
  {
   "id": "5ce2d474-e3ce-4914-8535-8a1370c1e7dc",
   "idx": 238,
   "data": [
    "angulus beatae voco",
    "KE_URS_75",
    "SRS_239",
    "Voveo subvenio aurum carbo cimentarius.",
    "7.0.8",
    "",
    ""
   ]
  },
  {
   "id": "c7c296fd-3136-499c-9e92-7e1b576bb128",
   "idx": 239,
   "data": [
    "talis tui solitudo",
    "KE_URS_92",
    "SRS_240",
    "Verbera angulus comedo dedecor calculus addo vetus.",
    "0.7.5",
    "",
    ""
   ]
  },
  {
   "id": "c46bdafb-c319-4091-ba6e-83454ecfff90",
   "idx": 240,
   "data": [
    "basium textus verbum",
    "KE_URS_73",
    "SRS_241",
    "Voluptatum adicio esse.",
    "2.8.4",
    "",
    ""
   ]
  },
  {
   "id": "7b7cba26-e477-4772-9bc8-e0e1ce0bead4",
   "idx": 241,
   "data": [
    "vestrum vicinus tabgo",
    "KE_URS_70",
    "SRS_242",
    "Suffoco conventus acer coma decor talus spiculum tyrannus.",
    "3.8.6",
    "Yes",
    ""
   ]
  },
  {
   "id": "f427b5a3-0bb3-4730-ac47-f0cfcf072f52",
   "idx": 242,
   "data": [
    "adopto demoror sint",
    "KE_URS_60",
    "SRS_243",
    "Corrumpo a aufero cervus ulciscor.",
    "4.3.4",
    "Yes",
    ""
   ]
  },
  {
   "id": "2d83c979-1db4-49eb-b752-780614e14323",
   "idx": 243,
   "data": [
    "nostrum ulciscor tyrannus",
    "KE_URS_68",
    "SRS_244",
    "Verumtamen aeneus utpote solium ver officia accommodo.",
    "8.1.2",
    "Yes",
    ""
   ]
  },
  {
   "id": "6b94bcbe-1359-4633-88d9-0391b8a4de32",
   "idx": 244,
   "data": [
    "patruus pecto cuppedia",
    "KE_URS_4",
    "SRS_245",
    "Bestia torrens ait.",
    "3.2.2",
    "Yes",
    ""
   ]
  },
  {
   "id": "9b4dc705-5523-4c9b-a9fb-63e0c7d67fc1",
   "idx": 245,
   "data": [
    "aeneus capillus substantia",
    "KE_URS_55",
    "SRS_246",
    "Vereor suffragium temporibus.",
    "5.7.7",
    "Yes",
    ""
   ]
  },
  {
   "id": "beab47ef-9ba7-47de-bebf-0846dac87d7a",
   "idx": 246,
   "data": [
    "claudeo volva turba",
    "KE_URS_52",
    "SRS_247",
    "Cohors thorax molestias acerbitas.",
    "1.7.9",
    "",
    ""
   ]
  },
  {
   "id": "17ca8728-e79b-42ab-b161-30feb5d7886a",
   "idx": 247,
   "data": [
    "basium textus verbum",
    "KE_URS_93",
    "SRS_248",
    "Calco thermae verbum textilis caput verecundia nobis cui sub curvo.",
    "2.3.8",
    "Yes",
    ""
   ]
  },
  {
   "id": "bb7b03c5-2d68-4448-9362-1f92e989ba65",
   "idx": 248,
   "data": [
    "cursim denique torrens",
    "KE_URS_55",
    "SRS_249",
    "Quas bis infit ventus pecco.",
    "5.0.5",
    "",
    ""
   ]
  },
  {
   "id": "84e17a53-b52b-41ef-8b70-a8c4a0919531",
   "idx": 249,
   "data": [
    "basium textus verbum",
    "KE_URS_40",
    "SRS_250",
    "Incidunt careo ut tam.",
    "6.0.1",
    "",
    ""
   ]
  },
  {
   "id": "377d18b9-5a31-49c6-884f-528c1e756285",
   "idx": 250,
   "data": [
    "tamquam abeo usus",
    "KE_URS_52",
    "SRS_251",
    "Trans tergiversatio ager cogo vulariter tergo comitatus cognatus cerno abundans.",
    "4.0.8",
    "",
    ""
   ]
  },
  {
   "id": "995af151-9738-4e40-a268-6b9ac77afa3b",
   "idx": 251,
   "data": [
    "vestrum vicinus tabgo",
    "KE_URS_65",
    "SRS_252",
    "A armarium odio capillus pectus aqua titulus repudiandae aperiam cui.",
    "3.1.2",
    "",
    ""
   ]
  },
  {
   "id": "a0f679cd-d1c8-403b-b0e8-64afd14ac4dd",
   "idx": 252,
   "data": [
    "vulgaris attollo audentia",
    "KE_URS_17",
    "SRS_253",
    "Bardus pel uredo aestivus.",
    "4.5.8",
    "Yes",
    ""
   ]
  },
  {
   "id": "41499cf2-7a96-4363-87c1-c76be8461d91",
   "idx": 253,
   "data": [
    "aeneus capillus substantia",
    "KE_URS_97",
    "SRS_254",
    "Consectetur quo caste acidus aliqua.",
    "9.3.0",
    "Yes",
    "N/A"
   ]
  },
  {
   "id": "0cbefa47-f263-444c-bfea-ea6db5df914d",
   "idx": 254,
   "data": [
    "claudeo volva turba",
    "KE_URS_12",
    "SRS_255",
    "Templum videlicet auditor admiratio auctor callide solus iusto.",
    "6.5.9",
    "Yes",
    ""
   ]
  },
  {
   "id": "4b73e1d9-40f5-4269-a9a4-c90f8991785f",
   "idx": 255,
   "data": [
    "maxime ascisco quasi",
    "KE_URS_11",
    "SRS_256",
    "Dens tribuo suscipit usitas triduana tendo curatio varius capio.",
    "4.8.1",
    "Yes",
    ""
   ]
  },
  {
   "id": "a35f4a3d-f928-448c-abdf-a55bcf2914ca",
   "idx": 256,
   "data": [
    "angulus beatae voco",
    "KE_URS_11",
    "SRS_257",
    "Aqua caelum sollicito creptio ara adipisci voluptatem varius centum.",
    "9.3.8",
    "",
    "N/A"
   ]
  },
  {
   "id": "a1fd2a00-5014-409d-9ad9-1318fe525912",
   "idx": 257,
   "data": [
    "arcus assentator assentator",
    "KE_URS_53",
    "SRS_258",
    "Caput antepono colo sophismata vulgivagus cum abscido.",
    "3.3.1",
    "Yes",
    ""
   ]
  },
  {
   "id": "96f9ce6d-0901-4bf3-981c-767cc15a66e3",
   "idx": 258,
   "data": [
    "perferendis talis culpa",
    "KE_URS_54",
    "SRS_259",
    "Ascit quae tempus ars.",
    "2.4.9",
    "",
    ""
   ]
  },
  {
   "id": "73cf44f9-97ca-4c0a-9259-385c787fc585",
   "idx": 259,
   "data": [
    "antepono aestivus tabgo",
    "KE_URS_7",
    "SRS_260",
    "Coaegresco eum corroboro.",
    "1.9.6",
    "Yes",
    ""
   ]
  },
  {
   "id": "9f990fbd-efb7-46b8-8841-ed83a72948fd",
   "idx": 260,
   "data": [
    "aliqua crepusculum celer",
    "KE_URS_37",
    "SRS_261",
    "Synagoga certe defendo temptatio cupiditas alter.",
    "0.9.4",
    "",
    ""
   ]
  },
  {
   "id": "fc52fe15-5425-4672-89aa-df702b6b95b5",
   "idx": 261,
   "data": [
    "bos baiulus surgo",
    "KE_URS_82",
    "SRS_262",
    "Bis cogito velut necessitatibus conventus solitudo aliquid sperno aggredior.",
    "9.6.5",
    "Yes",
    "N/A"
   ]
  },
  {
   "id": "09c4880a-027b-4f60-9962-77966b3c9f24",
   "idx": 262,
   "data": [
    "angulus beatae voco",
    "KE_URS_96",
    "SRS_263",
    "Carus charisma tardus quos combibo illo patruus depraedor pariatur tabernus.",
    "2.1.2",
    "Yes",
    ""
   ]
  },
  {
   "id": "246be4b7-b634-49af-bce6-aacd580eb674",
   "idx": 263,
   "data": [
    "aliquam coadunatio abutor",
    "KE_URS_98",
    "SRS_264",
    "Depopulo esse ratione ambitus adsuesco illo defendo conqueror.",
    "9.4.1",
    "Yes",
    ""
   ]
  },
  {
   "id": "8eb12697-6211-4d38-b824-7d21a7ea2be2",
   "idx": 264,
   "data": [
    "consuasor audentia ab",
    "KE_URS_89",
    "SRS_265",
    "Taedium asper audio.",
    "1.4.7",
    "",
    ""
   ]
  },
  {
   "id": "2f03ae3d-3509-4760-8402-7addf7a23b84",
   "idx": 265,
   "data": [
    "cogo a terra",
    "KE_URS_69",
    "SRS_266",
    "In sordeo comburo clam caecus provident textor ipsum confero assumenda.",
    "8.7.7",
    "",
    ""
   ]
  },
  {
   "id": "a86576b3-ca03-45f9-8cdd-274f9ee8dfee",
   "idx": 266,
   "data": [
    "arcus assentator assentator",
    "KE_URS_33",
    "SRS_267",
    "Auxilium adflicto aduro iste.",
    "2.7.9",
    "Yes",
    ""
   ]
  },
  {
   "id": "5d8aa897-4d7a-4479-ac47-caba3f74d787",
   "idx": 267,
   "data": [
    "vergo degenero succurro",
    "KE_URS_21",
    "SRS_268",
    "Asporto pecto suus.",
    "5.0.4",
    "Yes",
    ""
   ]
  },
  {
   "id": "14129dd9-0d67-4ab6-b6c0-a02448463bda",
   "idx": 268,
   "data": [
    "patruus pecto cuppedia",
    "KE_URS_67",
    "SRS_269",
    "Quo surgo blandior arto.",
    "2.9.8",
    "Yes",
    ""
   ]
  },
  {
   "id": "62db2819-65cd-4433-ac92-5b70ac078e7c",
   "idx": 269,
   "data": [
    "tamquam abeo usus",
    "KE_URS_43",
    "SRS_270",
    "Coerceo certe bellum.",
    "9.8.8",
    "",
    ""
   ]
  },
  {
   "id": "e849abf8-7a16-4870-93f9-d7ce522eef8a",
   "idx": 270,
   "data": [
    "adopto demoror sint",
    "KE_URS_53",
    "SRS_271",
    "Cruentus odio spargo campana claro appositus impedit decipio.",
    "4.5.2",
    "Yes",
    ""
   ]
  },
  {
   "id": "1cadcfc3-154a-4e8b-a093-8839fb69683f",
   "idx": 271,
   "data": [
    "antepono aestivus tabgo",
    "KE_URS_67",
    "SRS_272",
    "Vere molestias impedit ait calco acerbitas spoliatio.",
    "7.2.8",
    "Yes",
    ""
   ]
  },
  {
   "id": "39194c5f-9085-4b43-a0e2-9873518bc944",
   "idx": 272,
   "data": [
    "ducimus doloribus damnatio",
    "KE_URS_1",
    "SRS_273",
    "Spectaculum thermae tubineus sequi bellicus.",
    "2.4.0",
    "Yes",
    ""
   ]
  },
  {
   "id": "152814ea-9f65-4010-9aa8-043d23e412fa",
   "idx": 273,
   "data": [
    "aeneus capillus substantia",
    "KE_URS_82",
    "SRS_274",
    "Caries universe quisquam tempore.",
    "1.2.2",
    "Yes",
    ""
   ]
  },
  {
   "id": "f728791f-cfb7-4114-b737-c26123d0a8f1",
   "idx": 274,
   "data": [
    "vis aggredior capto",
    "KE_URS_4",
    "SRS_275",
    "Corona agnosco curriculum tero ars cilicium.",
    "0.7.7",
    "Yes",
    ""
   ]
  },
  {
   "id": "3c881b2b-490a-4c63-95a2-bc947c6bc2c2",
   "idx": 275,
   "data": [
    "ducimus doloribus damnatio",
    "KE_URS_58",
    "SRS_276",
    "Apostolus clamo volutabrum creber coepi amaritudo confido.",
    "1.5.2",
    "Yes",
    ""
   ]
  },
  {
   "id": "564d291a-c591-4b0b-ae8a-b7f2068a2f11",
   "idx": 276,
   "data": [
    "cogo a terra",
    "KE_URS_60",
    "SRS_277",
    "Animadverto amaritudo aqua amitto creta conventus stipes verto.",
    "9.7.5",
    "Yes",
    ""
   ]
  },
  {
   "id": "5e46fe0a-94f0-401a-b3c4-b5f0205183b8",
   "idx": 277,
   "data": [
    "aeneus capillus substantia",
    "KE_URS_47",
    "SRS_278",
    "Eligendi cumque quia aperio deporto.",
    "6.6.0",
    "Yes",
    ""
   ]
  },
  {
   "id": "0a5b737e-b6dd-4c37-9d71-94f8111dbe64",
   "idx": 278,
   "data": [
    "cursim denique torrens",
    "KE_URS_72",
    "SRS_279",
    "Antepono crepusculum suppellex urbanus.",
    "4.8.1",
    "Yes",
    "N/A"
   ]
  },
  {
   "id": "2568c950-f1f2-468e-bdeb-6a554ec77883",
   "idx": 279,
   "data": [
    "basium textus verbum",
    "KE_URS_41",
    "SRS_280",
    "Attollo texo sub ipsa stabilis tremo tergum.",
    "0.3.3",
    "Yes",
    ""
   ]
  },
  {
   "id": "ccbef28b-8112-4685-ac9c-bb7540856c5a",
   "idx": 280,
   "data": [
    "tamquam abeo usus",
    "KE_URS_40",
    "SRS_281",
    "Allatus succedo ago aperiam.",
    "5.3.5",
    "Yes",
    ""
   ]
  },
  {
   "id": "9e8b10e9-ea92-4e0b-bc78-196e9391f9ab",
   "idx": 281,
   "data": [
    "arcus assentator assentator",
    "KE_URS_32",
    "SRS_282",
    "Depromo degenero vix officia voluptatibus derideo.",
    "9.7.0",
    "",
    ""
   ]
  },
  {
   "id": "0c84e390-5b6d-4ca4-ab0a-612d246bc03b",
   "idx": 282,
   "data": [
    "ducimus doloribus damnatio",
    "KE_URS_56",
    "SRS_283",
    "Adfectus truculenter fugit toties aer.",
    "5.1.7",
    "",
    ""
   ]
  },
  {
   "id": "269adba5-9189-4b8d-a6cc-040121ba0beb",
   "idx": 283,
   "data": [
    "aliqua crepusculum celer",
    "KE_URS_47",
    "SRS_284",
    "Decet aggero deludo.",
    "8.0.9",
    "",
    ""
   ]
  },
  {
   "id": "d4e7cb2a-9a4f-42a7-bd99-acbf5531910f",
   "idx": 284,
   "data": [
    "arcus assentator assentator",
    "KE_URS_4",
    "SRS_285",
    "Cultura socius certe tendo odit universe sonitus acidus maiores tribuo.",
    "1.6.4",
    "Yes",
    ""
   ]
  },
  {
   "id": "a914feff-ae9f-4243-9ce7-7d2c95bafc3a",
   "idx": 285,
   "data": [
    "perferendis talis culpa",
    "KE_URS_75",
    "SRS_286",
    "Caecus claustrum adversus depopulo alter.",
    "0.3.9",
    "",
    "N/A"
   ]
  },
  {
   "id": "39df4779-c91e-4900-a84b-b800752317da",
   "idx": 286,
   "data": [
    "comparo aegre corroboro",
    "KE_URS_18",
    "SRS_287",
    "Dolorum adsum balbus creber caelestis harum crux virgo ipsam.",
    "6.0.2",
    "",
    ""
   ]
  },
  {
   "id": "9dc41ec0-6197-419a-9eda-5aa2fce9e99d",
   "idx": 287,
   "data": [
    "talis tui solitudo",
    "KE_URS_16",
    "SRS_288",
    "Denego acsi vinco tremo cribro acerbitas ex blanditiis assentator.",
    "6.8.1",
    "",
    ""
   ]
  },
  {
   "id": "89dcbbe5-13b2-40b3-b286-3e0b58f2da5c",
   "idx": 288,
   "data": [
    "bos baiulus surgo",
    "KE_URS_8",
    "SRS_289",
    "Validus crustulum copia administratio depopulo quo.",
    "6.3.4",
    "",
    ""
   ]
  },
  {
   "id": "3f2d01ca-cd5a-4ea6-a8b6-d5a5a2413dcc",
   "idx": 289,
   "data": [
    "conscendo una toties",
    "KE_URS_46",
    "SRS_290",
    "Ubi velociter armarium varius.",
    "1.9.6",
    "Yes",
    ""
   ]
  },
  {
   "id": "ea553b9f-67f2-4c9b-9c9f-38265da86713",
   "idx": 290,
   "data": [
    "cogo a terra",
    "KE_URS_18",
    "SRS_291",
    "Strenuus tametsi velit tener aetas pauper amoveo amitto deleo.",
    "8.4.6",
    "Yes",
    ""
   ]
  },
  {
   "id": "d916bd36-fee8-4012-b8b9-df697bcc0abd",
   "idx": 291,
   "data": [
    "conscendo una toties",
    "KE_URS_76",
    "SRS_292",
    "Bardus defungo terreo adiuvo consequuntur sto illo corporis.",
    "1.7.6",
    "Yes",
    ""
   ]
  },
  {
   "id": "46590f2e-c33e-4c3f-ad49-fd9d05cbc2fd",
   "idx": 292,
   "data": [
    "ustilo creo crebro",
    "KE_URS_24",
    "SRS_293",
    "Aequitas distinctio adaugeo ex sponte adfero usque vicinus deporto.",
    "9.8.4",
    "Yes",
    ""
   ]
  },
  {
   "id": "4ebdd67f-0167-41a6-8c5b-227347554aa3",
   "idx": 293,
   "data": [
    "basium textus verbum",
    "KE_URS_53",
    "SRS_294",
    "Consectetur patria apostolus assentator.",
    "3.5.6",
    "",
    ""
   ]
  },
  {
   "id": "3ac61eb2-08c4-421b-969b-686addd49d17",
   "idx": 294,
   "data": [
    "talis tui solitudo",
    "KE_URS_83",
    "SRS_295",
    "Damno videlicet acceptus demens.",
    "9.0.2",
    "",
    ""
   ]
  },
  {
   "id": "31e74b41-4569-4016-ae2d-c5c69b999aba",
   "idx": 295,
   "data": [
    "ustilo creo crebro",
    "KE_URS_60",
    "SRS_296",
    "Sumptus voluptates atavus provident cito correptius cunctatio fugiat cursus.",
    "2.6.5",
    "Yes",
    "N/A"
   ]
  },
  {
   "id": "83852f1e-5400-4563-9970-e069d6b27b06",
   "idx": 296,
   "data": [
    "arcus assentator assentator",
    "KE_URS_10",
    "SRS_297",
    "Ducimus tenax accusamus balbus officia chirographum absconditus fugiat assumenda ventosus.",
    "2.1.5",
    "",
    ""
   ]
  },
  {
   "id": "81a96764-a991-49b0-809c-761b72376416",
   "idx": 297,
   "data": [
    "antepono aestivus tabgo",
    "KE_URS_86",
    "SRS_298",
    "Sordeo suscipit cunae ambitus.",
    "9.7.9",
    "Yes",
    ""
   ]
  },
  {
   "id": "990a1d44-d36f-404a-a0af-e3e0794d94d8",
   "idx": 298,
   "data": [
    "veritas tabesco delibero",
    "KE_URS_59",
    "SRS_299",
    "Altus peior delectatio usitas teneo vulticulus attonbitus demo.",
    "8.6.4",
    "",
    ""
   ]
  },
  {
   "id": "73b3aa5d-ed6a-4208-857b-ba5e2069039f",
   "idx": 299,
   "data": [
    "claudeo volva turba",
    "KE_URS_34",
    "SRS_300",
    "Cenaculum votum summopere consequuntur temperantia.",
    "6.8.5",
    "Yes",
    ""
   ]
  },
  {
   "id": "8df22e1f-bc57-4b7f-a744-67aeb7a07c23",
   "idx": 300,
   "data": [
    "cursim denique torrens",
    "KE_URS_23",
    "SRS_301",
    "Accusator avarus coaegresco cognatus patria umquam caterva.",
    "5.1.9",
    "Yes",
    ""
   ]
  },
  {
   "id": "4e9321e5-902e-427d-8d18-3ead508c55b6",
   "idx": 301,
   "data": [
    "patruus pecto cuppedia",
    "KE_URS_50",
    "SRS_302",
    "Carbo adipisci considero cervus ocer talus super credo.",
    "9.3.0",
    "Yes",
    "N/A"
   ]
  },
  {
   "id": "ba932589-b3fe-4062-9316-a2b685923c76",
   "idx": 302,
   "data": [
    "varietas utrimque bellum",
    "KE_URS_67",
    "SRS_303",
    "Teres vulariter uter ulterius consuasor.",
    "1.2.0",
    "Yes",
    ""
   ]
  },
  {
   "id": "20cd4314-958c-4bc2-9770-9c55198e2054",
   "idx": 303,
   "data": [
    "sordeo civis trans",
    "KE_URS_58",
    "SRS_304",
    "Tergiversatio valde libero ars.",
    "0.5.7",
    "",
    ""
   ]
  },
  {
   "id": "e8d0cd6d-3a41-48d9-a8ee-6535ea7b11ec",
   "idx": 304,
   "data": [
    "claudeo volva turba",
    "KE_URS_76",
    "SRS_305",
    "Arguo vorax tantum suppono cervus spiritus.",
    "3.6.2",
    "",
    ""
   ]
  },
  {
   "id": "6463cf29-e32f-4f6b-ad27-2deb9bac3770",
   "idx": 305,
   "data": [
    "somnus ratione valde",
    "KE_URS_53",
    "SRS_306",
    "Vel amoveo tenuis cauda.",
    "9.8.8",
    "",
    ""
   ]
  },
  {
   "id": "b1dc9650-b830-4655-b7f0-8a89292b4030",
   "idx": 306,
   "data": [
    "sordeo civis trans",
    "KE_URS_38",
    "SRS_307",
    "Vorago solvo vulgivagus.",
    "3.5.7",
    "Yes",
    ""
   ]
  },
  {
   "id": "949fdd49-1b93-4f16-bd00-1d51ce7bc360",
   "idx": 307,
   "data": [
    "vacuus nostrum doloribus",
    "KE_URS_38",
    "SRS_308",
    "Combibo vestigium alo paulatim bos numquam usque ullam molestias.",
    "0.7.9",
    "Yes",
    ""
   ]
  },
  {
   "id": "575193fe-babb-4e19-96f1-c4eb2de3853c",
   "idx": 308,
   "data": [
    "perferendis talis culpa",
    "KE_URS_72",
    "SRS_309",
    "Bos statua collum decens dignissimos despecto thorax amiculum.",
    "4.9.7",
    "Yes",
    ""
   ]
  },
  {
   "id": "330fa83d-7613-4bbb-aa1b-d1951ac8b4be",
   "idx": 309,
   "data": [
    "ducimus doloribus damnatio",
    "KE_URS_94",
    "SRS_310",
    "Catena tabella demonstro mollitia accendo corroboro adicio.",
    "0.2.7",
    "",
    ""
   ]
  },
  {
   "id": "5efbee4b-25f0-4c18-bc5a-5bfadd3f8b38",
   "idx": 310,
   "data": [
    "patruus pecto cuppedia",
    "KE_URS_12",
    "SRS_311",
    "Aperio contra vinco calcar solutio subito voluptatem vomica tumultus tamdiu.",
    "2.7.3",
    "Yes",
    ""
   ]
  },
  {
   "id": "4402ec30-4fca-4ce0-adb7-12af7685264c",
   "idx": 311,
   "data": [
    "consuasor audentia ab",
    "KE_URS_38",
    "SRS_312",
    "Sumo patria odio curatio victoria cervus ager cilicium crapula.",
    "9.2.6",
    "Yes",
    ""
   ]
  },
  {
   "id": "77cb7b72-2b60-477d-b495-da162e9f9d9b",
   "idx": 312,
   "data": [
    "vergo degenero succurro",
    "KE_URS_6",
    "SRS_313",
    "Dolore terra magni thesaurus teres.",
    "9.6.8",
    "Yes",
    ""
   ]
  },
  {
   "id": "745299f5-17a0-4871-b93d-1ecca203c4be",
   "idx": 313,
   "data": [
    "aliquam coadunatio abutor",
    "KE_URS_11",
    "SRS_314",
    "Concido crur adeo non vomer arma.",
    "7.4.6",
    "Yes",
    ""
   ]
  },
  {
   "id": "4bba6654-820d-42b4-9d65-040e261a1ac4",
   "idx": 314,
   "data": [
    "aliqua crepusculum celer",
    "KE_URS_33",
    "SRS_315",
    "Adduco decretum eligendi ad cariosus.",
    "8.8.9",
    "Yes",
    ""
   ]
  },
  {
   "id": "274141b7-97fa-4fdd-a80f-e8b8fc972611",
   "idx": 315,
   "data": [
    "adopto demoror sint",
    "KE_URS_95",
    "SRS_316",
    "Constans dolorem uberrime certus demergo censura bellicus.",
    "8.7.1",
    "",
    ""
   ]
  },
  {
   "id": "5c91b508-5671-4f47-b80b-eaf30b698369",
   "idx": 316,
   "data": [
    "consuasor audentia ab",
    "KE_URS_5",
    "SRS_317",
    "Adnuo asper denuo via.",
    "7.5.3",
    "",
    "N/A"
   ]
  },
  {
   "id": "4086f332-6105-4035-9b70-ee3326b1673c",
   "idx": 317,
   "data": [
    "perferendis talis culpa",
    "KE_URS_48",
    "SRS_318",
    "Studio supra cubitum adnuo claudeo.",
    "3.4.8",
    "Yes",
    ""
   ]
  },
  {
   "id": "fc407fd3-1b3a-4d74-8bb0-3cef3bfb2e6c",
   "idx": 318,
   "data": [
    "depromo accusamus paens",
    "KE_URS_32",
    "SRS_319",
    "Venia cursim vespillo decor aegrus amitto commemoro tardus tracto abduco.",
    "6.2.6",
    "Yes",
    ""
   ]
  },
  {
   "id": "6e66e75f-c19d-478a-bf8d-fce2622d28a7",
   "idx": 319,
   "data": [
    "aliquam coadunatio abutor",
    "KE_URS_68",
    "SRS_320",
    "Tredecim trans coepi bonus nesciunt deputo neque attonbitus tribuo.",
    "0.0.8",
    "Yes",
    ""
   ]
  },
  {
   "id": "152b2163-d8fb-463a-a98e-b15dc60292c9",
   "idx": 320,
   "data": [
    "conscendo una toties",
    "KE_URS_68",
    "SRS_321",
    "Quae terebro cado.",
    "0.0.6",
    "",
    ""
   ]
  },
  {
   "id": "824009f0-6b3e-4609-ae64-83997b6c7c06",
   "idx": 321,
   "data": [
    "sufficio odit vesica",
    "KE_URS_85",
    "SRS_322",
    "Verecundia pauci torqueo stultus derelinquo pecus templum.",
    "3.8.4",
    "",
    ""
   ]
  },
  {
   "id": "4a11da39-cfa6-4dd7-b840-2b62319bbb63",
   "idx": 322,
   "data": [
    "vulgaris attollo audentia",
    "KE_URS_62",
    "SRS_323",
    "Vulpes turba decumbo aut eius vorax tertius copiose.",
    "1.9.9",
    "",
    ""
   ]
  },
  {
   "id": "01f45bf9-c63b-478b-bde6-4f9f87c9954b",
   "idx": 323,
   "data": [
    "nostrum ulciscor tyrannus",
    "KE_URS_94",
    "SRS_324",
    "Comburo abundans cervus velum carpo dolorum.",
    "0.8.0",
    "",
    ""
   ]
  },
  {
   "id": "f090b096-e975-4d5c-ab9d-e6f88914bd15",
   "idx": 324,
   "data": [
    "depromo accusamus paens",
    "KE_URS_96",
    "SRS_325",
    "Angelus facere dignissimos voluptate quibusdam vallum aqua modi sperno provident.",
    "7.1.3",
    "Yes",
    ""
   ]
  },
  {
   "id": "560336cd-e805-4272-b577-9eecb26d0784",
   "idx": 325,
   "data": [
    "nostrum ulciscor tyrannus",
    "KE_URS_95",
    "SRS_326",
    "Spero totidem eveniet venio terra spero laborum viduo.",
    "3.4.5",
    "Yes",
    ""
   ]
  },
  {
   "id": "fde2e574-8991-4264-aa24-04682e7344db",
   "idx": 326,
   "data": [
    "vacuus nostrum doloribus",
    "KE_URS_95",
    "SRS_327",
    "Appello audacia vulnero.",
    "3.4.4",
    "Yes",
    ""
   ]
  },
  {
   "id": "a9ab721e-ded4-4414-934f-7ae0d1062cb1",
   "idx": 327,
   "data": [
    "adopto demoror sint",
    "KE_URS_69",
    "SRS_328",
    "Numquam vociferor aspernatur crinis tabgo.",
    "3.8.5",
    "Yes",
    "N/A"
   ]
  },
  {
   "id": "dbcf5ab3-8318-4af2-98eb-21b13eb4d68e",
   "idx": 328,
   "data": [
    "perferendis talis culpa",
    "KE_URS_41",
    "SRS_329",
    "Verumtamen urbanus pauci approbo.",
    "7.9.5",
    "Yes",
    ""
   ]
  },
  {
   "id": "c793bb61-3c19-40e7-be43-2d80dffed0be",
   "idx": 329,
   "data": [
    "patruus pecto cuppedia",
    "KE_URS_19",
    "SRS_330",
    "Sumo solum triumphus clarus sum tollo velociter.",
    "9.5.2",
    "Yes",
    ""
   ]
  },
  {
   "id": "9e93b864-7e3b-4dfd-bfe8-8bd41478490e",
   "idx": 330,
   "data": [
    "tamquam abeo usus",
    "KE_URS_95",
    "SRS_331",
    "Deporto sto cribro calco doloribus.",
    "8.5.8",
    "Yes",
    ""
   ]
  },
  {
   "id": "f4a08788-7c5d-4fcd-9314-5a6cb497470c",
   "idx": 331,
   "data": [
    "cogo a terra",
    "KE_URS_76",
    "SRS_332",
    "Defessus colo sopor.",
    "2.4.4",
    "",
    ""
   ]
  },
  {
   "id": "768979a9-1aa0-422e-9be2-2e1b62bdf81d",
   "idx": 332,
   "data": [
    "antepono aestivus tabgo",
    "KE_URS_99",
    "SRS_333",
    "Torrens accommodo subvenio cribro.",
    "1.6.0",
    "",
    ""
   ]
  },
  {
   "id": "81037d27-2f5f-485a-b211-40ec248d2b12",
   "idx": 333,
   "data": [
    "tamquam abeo usus",
    "KE_URS_69",
    "SRS_334",
    "Coerceo eligendi vinco vilitas explicabo ciminatio crastinus tenetur thymum.",
    "6.4.0",
    "Yes",
    ""
   ]
  },
  {
   "id": "aea9ab07-ccc9-4a2b-9146-17c94c51c0de",
   "idx": 334,
   "data": [
    "varietas utrimque bellum",
    "KE_URS_75",
    "SRS_335",
    "Desino voluptate traho.",
    "0.7.4",
    "",
    ""
   ]
  },
  {
   "id": "97cb7006-9f07-4586-badb-ab179a582a04",
   "idx": 335,
   "data": [
    "aliquam coadunatio abutor",
    "KE_URS_89",
    "SRS_336",
    "Ullus turpis cinis spargo cumque.",
    "7.9.8",
    "Yes",
    ""
   ]
  },
  {
   "id": "b718f66c-bd71-401f-b21a-a4add68c4ad6",
   "idx": 336,
   "data": [
    "vis aggredior capto",
    "KE_URS_2",
    "SRS_337",
    "Decet avaritia volaticus sonitus ultio.",
    "6.5.7",
    "Yes",
    ""
   ]
  },
  {
   "id": "4699f3f5-5b72-45c9-8740-b34ffe30c87c",
   "idx": 337,
   "data": [
    "depromo accusamus paens",
    "KE_URS_98",
    "SRS_338",
    "Asporto vetus comptus demergo.",
    "5.3.0",
    "",
    ""
   ]
  },
  {
   "id": "f6e71012-56d3-48ef-abfa-01cabf50e770",
   "idx": 338,
   "data": [
    "depromo accusamus paens",
    "KE_URS_22",
    "SRS_339",
    "Adduco acsi capio.",
    "6.4.9",
    "Yes",
    ""
   ]
  },
  {
   "id": "acb41918-8d06-4796-a0e1-4c8ed049f1d0",
   "idx": 339,
   "data": [
    "ducimus doloribus damnatio",
    "KE_URS_61",
    "SRS_340",
    "Illum eaque admiratio reiciendis certe defaeco solutio.",
    "0.8.8",
    "Yes",
    ""
   ]
  },
  {
   "id": "3b2986d8-89c9-406b-b60d-a179e0d6f961",
   "idx": 340,
   "data": [
    "vacuus nostrum doloribus",
    "KE_URS_19",
    "SRS_341",
    "Texo textor stipes vigor arbor.",
    "7.6.2",
    "Yes",
    ""
   ]
  },
  {
   "id": "e34f83ea-295f-4318-9b98-d7c9e59efd84",
   "idx": 341,
   "data": [
    "sordeo civis trans",
    "KE_URS_14",
    "SRS_342",
    "Cunctatio esse degusto ab benigne amplexus libero verecundia vitiosus accusantium.",
    "5.5.6",
    "Yes",
    ""
   ]
  },
  {
   "id": "e2b96278-70e7-4c4e-8728-6867b4b34807",
   "idx": 342,
   "data": [
    "adopto demoror sint",
    "KE_URS_29",
    "SRS_343",
    "Adipisci non voro tergiversatio tumultus comparo adnuo praesentium.",
    "3.2.2",
    "Yes",
    ""
   ]
  },
  {
   "id": "b8531341-b166-46f0-b22e-ed1a5e708804",
   "idx": 343,
   "data": [
    "basium textus verbum",
    "KE_URS_7",
    "SRS_344",
    "Tollo admoveo civis surculus aptus crudelis aranea tabernus tricesimus alo.",
    "7.7.2",
    "Yes",
    ""
   ]
  },
  {
   "id": "6a81928c-f7a8-4bc6-8f5d-17f6ea7d40b2",
   "idx": 344,
   "data": [
    "somnus ratione valde",
    "KE_URS_38",
    "SRS_345",
    "Virga ager accusantium tripudio spiritus fugit spectaculum deficio tutis ultio.",
    "0.8.9",
    "Yes",
    ""
   ]
  },
  {
   "id": "a755a9ab-8622-4d5e-a10f-df9f264c0931",
   "idx": 345,
   "data": [
    "bos baiulus surgo",
    "KE_URS_43",
    "SRS_346",
    "Crinis totus ulterius vestigium defetiscor.",
    "3.2.1",
    "",
    ""
   ]
  },
  {
   "id": "a897bb98-4c68-4105-980f-8db16849312f",
   "idx": 346,
   "data": [
    "tamquam abeo usus",
    "KE_URS_58",
    "SRS_347",
    "Apparatus tabella carcer.",
    "1.2.3",
    "Yes",
    ""
   ]
  },
  {
   "id": "ef6a799b-75e7-4dfd-a163-16b242146d79",
   "idx": 347,
   "data": [
    "vulgaris attollo audentia",
    "KE_URS_99",
    "SRS_348",
    "Tametsi vomica corrumpo corpus.",
    "7.6.3",
    "Yes",
    ""
   ]
  },
  {
   "id": "43c27462-1d74-4beb-9217-3a75a77a1020",
   "idx": 348,
   "data": [
    "nostrum ulciscor tyrannus",
    "KE_URS_25",
    "SRS_349",
    "Antepono custodia aveho quis abbas aurum velum.",
    "8.3.7",
    "Yes",
    ""
   ]
  },
  {
   "id": "a3655d88-8c80-4be1-968f-89c370b56304",
   "idx": 349,
   "data": [
    "veritas tabesco delibero",
    "KE_URS_77",
    "SRS_350",
    "Aduro voluptatibus ulterius voluptate.",
    "5.2.9",
    "Yes",
    ""
   ]
  },
  {
   "id": "e63bdd40-536d-4fd8-8b44-2391458f8ec8",
   "idx": 350,
   "data": [
    "basium textus verbum",
    "KE_URS_18",
    "SRS_351",
    "Admiratio stillicidium veritas defluo eos demonstro vacuus despecto paulatim.",
    "4.2.6",
    "",
    "N/A"
   ]
  },
  {
   "id": "48e2bcea-adfa-46e9-9c61-11712e6bcaff",
   "idx": 351,
   "data": [
    "vis aggredior capto",
    "KE_URS_61",
    "SRS_352",
    "Ter avaritia verumtamen cum tonsor libero victoria vae.",
    "7.7.2",
    "Yes",
    ""
   ]
  },
  {
   "id": "f63c1871-70a5-4954-b750-2ec8c820b61b",
   "idx": 352,
   "data": [
    "ustilo creo crebro",
    "KE_URS_33",
    "SRS_353",
    "Audacia ater speculum adfero tero nesciunt capillus adhuc tolero.",
    "7.1.8",
    "Yes",
    ""
   ]
  },
  {
   "id": "e9a60afb-2ef7-4522-9148-1d849042a254",
   "idx": 353,
   "data": [
    "basium textus verbum",
    "KE_URS_85",
    "SRS_354",
    "Cilicium vereor quam.",
    "7.4.3",
    "Yes",
    ""
   ]
  },
  {
   "id": "1f76f716-c1ca-42ce-b865-7d7f81033e1e",
   "idx": 354,
   "data": [
    "vergo degenero succurro",
    "KE_URS_81",
    "SRS_355",
    "Adficio thema vulnus.",
    "8.8.8",
    "Yes",
    ""
   ]
  },
  {
   "id": "517d1fea-16f1-46d1-a576-7a594e396840",
   "idx": 355,
   "data": [
    "sordeo civis trans",
    "KE_URS_10",
    "SRS_356",
    "Beatus consequatur cultura depulso in agnosco copiose comminor.",
    "5.7.0",
    "Yes",
    ""
   ]
  },
  {
   "id": "ee1584ca-ce80-40fc-87a3-001acc00bdcc",
   "idx": 356,
   "data": [
    "maxime ascisco quasi",
    "KE_URS_1",
    "SRS_357",
    "Validus temptatio teres capto.",
    "9.7.1",
    "",
    ""
   ]
  },
  {
   "id": "ee1703b3-5cd2-4374-a09d-56bb7f56c4ca",
   "idx": 357,
   "data": [
    "maxime ascisco quasi",
    "KE_URS_52",
    "SRS_358",
    "Pel ocer aptus vito voluptas ambitus defessus pauper arbustum.",
    "8.3.8",
    "Yes",
    ""
   ]
  },
  {
   "id": "d607cc23-33cb-4bae-8eca-a1fc925c5a93",
   "idx": 358,
   "data": [
    "vestrum vicinus tabgo",
    "KE_URS_36",
    "SRS_359",
    "Deleo uxor infit depopulo cura.",
    "9.1.1",
    "",
    ""
   ]
  },
  {
   "id": "b5487d2f-e711-4206-9999-1952693a6605",
   "idx": 359,
   "data": [
    "basium textus verbum",
    "KE_URS_9",
    "SRS_360",
    "Cattus cultellus sophismata antea deludo dens creo tamdiu adopto aequus.",
    "7.8.3",
    "Yes",
    ""
   ]
  },
  {
   "id": "da6bd871-4fc7-4568-a966-b21141cb1a5f",
   "idx": 360,
   "data": [
    "aeneus capillus substantia",
    "KE_URS_71",
    "SRS_361",
    "Suffragium clam thema basium.",
    "3.0.6",
    "",
    ""
   ]
  },
  {
   "id": "a64b59ea-86b0-4779-bd1f-ec533ac7c69b",
   "idx": 361,
   "data": [
    "vergo degenero succurro",
    "KE_URS_48",
    "SRS_362",
    "Benigne appositus cetera strues vinum caritas animadverto.",
    "3.3.1",
    "",
    ""
   ]
  },
  {
   "id": "b3a359e1-2fb6-49b5-8647-1fbdbcab6286",
   "idx": 362,
   "data": [
    "vulgaris attollo audentia",
    "KE_URS_4",
    "SRS_363",
    "Defessus officia abstergo ipsa auxilium creo caries.",
    "1.1.5",
    "",
    ""
   ]
  },
  {
   "id": "12bc4d5f-0486-4b97-bcb3-82a537e89c35",
   "idx": 363,
   "data": [
    "claudeo volva turba",
    "KE_URS_50",
    "SRS_364",
    "Vulgivagus ventosus tibi urbs caute chirographum ut.",
    "5.3.6",
    "Yes",
    ""
   ]
  },
  {
   "id": "5076e3a6-a5ce-4ee3-992d-86e4e5ef13d7",
   "idx": 364,
   "data": [
    "arcus assentator assentator",
    "KE_URS_43",
    "SRS_365",
    "Substantia audeo bonus depono ara alius.",
    "7.4.4",
    "",
    ""
   ]
  }
 ]
}